<mujoco model="arena">
  <compiler angle="radian" autolimits="true" meshdir="meshes"/>
  <option timestep="0.002" integrator="implicitfast" gravity="0 0 -9.81"/>
  <default>
    <default class="wheel"><geom type="cylinder" size="0.028 0.01" zaxis="0 1 0"
      rgba="0.12 0.12 0.12 1" friction="1.4 0.01 0.001" condim="3"/>
      <joint type="hinge" axis="0 1 0" damping="0.015" armature="0.003"/></default>
    <default class="caster"><geom type="sphere" size="0.008" rgba="0.4 0.4 0.4 1" condim="1"/></default>
    <default class="camlink"><geom contype="0" conaffinity="0" rgba="0.2 0.2 0.22 1"/>
      <joint damping="0.6"/></default>
  </default>
  <visual>
    <global offwidth="1280" offheight="1280"/>
    <headlight diffuse="0.5 0.5 0.5" ambient="0.45 0.45 0.45"/>
    <quality shadowsize="0"/>
  </visual>
  <asset>
    <material name="floor" rgba="0.5 0.5 0.52 1" reflectance="0.05"/>
    <material name="wall" rgba="0.88 0.88 0.86 1"/>
    <mesh name="pyramid" file="pyramid.obj" scale="0.07 0.07 0.07"/>
    <mesh name="prism"   file="prism.obj"   scale="0.07 0.07 0.07"/>
    <texture name="t0" type="2d" file="textures/tex0.png"/>
    <material name="m0" texture="t0" texrepeat="2 2"/>
    <texture name="t1" type="2d" file="textures/tex1.png"/>
    <material name="m1" texture="t1" texrepeat="2 2"/>
    <texture name="t2" type="2d" file="textures/tex2.png"/>
    <material name="m2" texture="t2" texrepeat="2 2"/>
    <texture name="t3" type="2d" file="textures/tex3.png"/>
    <material name="m3" texture="t3" texrepeat="2 2"/>
    <texture name="t4" type="2d" file="textures/tex4.png"/>
    <material name="m4" texture="t4" texrepeat="2 2"/>
    <texture name="t5" type="2d" file="textures/tex5.png"/>
    <material name="m5" texture="t5" texrepeat="2 2"/>
    <texture name="t6" type="2d" file="textures/tex6.png"/>
    <material name="m6" texture="t6" texrepeat="2 2"/>
    <texture name="t7" type="2d" file="textures/tex7.png"/>
    <material name="m7" texture="t7" texrepeat="2 2"/>
  </asset>
  <worldbody>
    <light name="key"  pos="-2 -2 4" dir="0.5 0.5 -1" diffuse="0.6 0.6 0.6" castshadow="false"/>
    <light name="fill" pos="2 2 4"   dir="-0.5 -0.5 -1" diffuse="0.5 0.5 0.5" castshadow="false"/>
    <geom name="floor" type="plane" size="0 0 0.05" material="floor" condim="3" friction="1.0 0.005 0.0001"/>
    <geom type="box" pos="-4.6 0 1.3" size="0.05 4.5 1.3" material="wall"/>
    <geom type="box" pos=" 4.6 0 1.3" size="0.05 4.5 1.3" material="wall"/>
    <geom type="box" pos="0 -4.5 1.3" size="4.6 0.05 1.3" material="wall"/>
    <geom type="box" pos="0  4.5 1.3" size="4.6 0.05 1.3" material="wall"/>
    <body pos="-3.2 -2.4 0" euler="0 0 0.0">
      <geom type="box" pos="0 0 0.74" size="0.6 0.3 0.02" rgba="0.85 0.82 0.78 1"/>
      <geom type="box" pos="-0.55 -0.25 0.37" size="0.02 0.02 0.37" rgba="0.12 0.12 0.12 1"/>
      <geom type="box" pos="-0.55 0.25 0.37" size="0.02 0.02 0.37" rgba="0.12 0.12 0.12 1"/>
      <geom type="box" pos="0.55 -0.25 0.37" size="0.02 0.02 0.37" rgba="0.12 0.12 0.12 1"/>
      <geom type="box" pos="0.55 0.25 0.37" size="0.02 0.02 0.37" rgba="0.12 0.12 0.12 1"/>
      <geom type="box" pos="0.1 0 0.86" size="0.16 0.02 0.1" rgba="0.04 0.04 0.05 1"/>
    </body>
    <body pos="-2.6500000000000004 -1.8499999999999999 0" euler="0 0 3.1416">
      <geom type="box" pos="0 0 1.0" size="0.16 0.11 0.22" rgba="0.1 0.1 0.12 1"/>
      <geom type="sphere" pos="0 0 1.32" size="0.1" rgba="0.82 0.66 0.54 1"/>
      <geom type="box" pos="0.36 -0.08 0.4" size="0.07 0.06 0.4" rgba="0.1 0.1 0.12 1"/>
      <geom type="box" pos="0.36 0.08 0.4" size="0.07 0.06 0.4" rgba="0.1 0.1 0.12 1"/>
    </body>
    <body pos="-3.2 -1.2 0" euler="0 0 0.0">
      <geom type="box" pos="0 0 0.74" size="0.6 0.3 0.02" rgba="0.6 0.45 0.3 1"/>
      <geom type="box" pos="-0.55 -0.25 0.37" size="0.02 0.02 0.37" rgba="0.12 0.12 0.12 1"/>
      <geom type="box" pos="-0.55 0.25 0.37" size="0.02 0.02 0.37" rgba="0.12 0.12 0.12 1"/>
      <geom type="box" pos="0.55 -0.25 0.37" size="0.02 0.02 0.37" rgba="0.12 0.12 0.12 1"/>
      <geom type="box" pos="0.55 0.25 0.37" size="0.02 0.02 0.37" rgba="0.12 0.12 0.12 1"/>
      <geom type="box" pos="0.1 0 0.86" size="0.16 0.02 0.1" rgba="0.04 0.04 0.05 1"/>
    </body>
    <body pos="-2.7 -1.2 0"><geom type="cylinder" pos="0 0 0.6" size="0.16 0.02" rgba="0.2 0.2 0.22 1"/><geom type="cylinder" pos="0 0 0.3" size="0.025 0.3" rgba="0.3 0.3 0.32 1"/></body>
    <body pos="-3.2 0 0" euler="0 0 0.0">
      <geom type="box" pos="0 0 0.74" size="0.6 0.3 0.02" rgba="0.75 0.76 0.8 1"/>
      <geom type="box" pos="-0.55 -0.25 0.37" size="0.02 0.02 0.37" rgba="0.12 0.12 0.12 1"/>
      <geom type="box" pos="-0.55 0.25 0.37" size="0.02 0.02 0.37" rgba="0.12 0.12 0.12 1"/>
      <geom type="box" pos="0.55 -0.25 0.37" size="0.02 0.02 0.37" rgba="0.12 0.12 0.12 1"/>
      <geom type="box" pos="0.55 0.25 0.37" size="0.02 0.02 0.37" rgba="0.12 0.12 0.12 1"/>
      <geom type="box" pos="0.1 0 0.86" size="0.16 0.02 0.1" rgba="0.04 0.04 0.05 1"/>
    </body>
    <body pos="-2.6500000000000004 0 0" euler="0 0 3.1416">
      <geom type="box" pos="0 0 1.0" size="0.16 0.11 0.22" rgba="0.5 0.12 0.12 1"/>
      <geom type="sphere" pos="0 0 1.32" size="0.1" rgba="0.82 0.66 0.54 1"/>
      <geom type="box" pos="0.36 -0.08 0.4" size="0.07 0.06 0.4" rgba="0.1 0.1 0.12 1"/>
      <geom type="box" pos="0.36 0.08 0.4" size="0.07 0.06 0.4" rgba="0.1 0.1 0.12 1"/>
    </body>
    <body pos="-3.2 1.2 0" euler="0 0 0.0">
      <geom type="box" pos="0 0 0.74" size="0.6 0.3 0.02" rgba="0.85 0.82 0.78 1"/>
      <geom type="box" pos="-0.55 -0.25 0.37" size="0.02 0.02 0.37" rgba="0.12 0.12 0.12 1"/>
      <geom type="box" pos="-0.55 0.25 0.37" size="0.02 0.02 0.37" rgba="0.12 0.12 0.12 1"/>
      <geom type="box" pos="0.55 -0.25 0.37" size="0.02 0.02 0.37" rgba="0.12 0.12 0.12 1"/>
      <geom type="box" pos="0.55 0.25 0.37" size="0.02 0.02 0.37" rgba="0.12 0.12 0.12 1"/>
      <geom type="box" pos="0.1 0 0.86" size="0.16 0.02 0.1" rgba="0.04 0.04 0.05 1"/>
    </body>
    <body pos="-2.7 1.2 0"><geom type="cylinder" pos="0 0 0.6" size="0.16 0.02" rgba="0.2 0.2 0.22 1"/><geom type="cylinder" pos="0 0 0.3" size="0.025 0.3" rgba="0.3 0.3 0.32 1"/></body>
    <body pos="-3.2 2.4 0" euler="0 0 0.0">
      <geom type="box" pos="0 0 0.74" size="0.6 0.3 0.02" rgba="0.6 0.45 0.3 1"/>
      <geom type="box" pos="-0.55 -0.25 0.37" size="0.02 0.02 0.37" rgba="0.12 0.12 0.12 1"/>
      <geom type="box" pos="-0.55 0.25 0.37" size="0.02 0.02 0.37" rgba="0.12 0.12 0.12 1"/>
      <geom type="box" pos="0.55 -0.25 0.37" size="0.02 0.02 0.37" rgba="0.12 0.12 0.12 1"/>
      <geom type="box" pos="0.55 0.25 0.37" size="0.02 0.02 0.37" rgba="0.12 0.12 0.12 1"/>
      <geom type="box" pos="0.1 0 0.86" size="0.16 0.02 0.1" rgba="0.04 0.04 0.05 1"/>
    </body>
    <body pos="-2.6500000000000004 1.8499999999999999 0" euler="0 0 3.1416">
      <geom type="box" pos="0 0 1.0" size="0.16 0.11 0.22" rgba="0.1 0.3 0.25 1"/>
      <geom type="sphere" pos="0 0 1.32" size="0.1" rgba="0.82 0.66 0.54 1"/>
      <geom type="box" pos="0.36 -0.08 0.4" size="0.07 0.06 0.4" rgba="0.1 0.1 0.12 1"/>
      <geom type="box" pos="0.36 0.08 0.4" size="0.07 0.06 0.4" rgba="0.1 0.1 0.12 1"/>
    </body>
    <body pos="3.2 -2.4 0" euler="0 0 3.1416">
      <geom type="box" pos="0 0 0.74" size="0.6 0.3 0.02" rgba="0.75 0.76 0.8 1"/>
      <geom type="box" pos="-0.55 -0.25 0.37" size="0.02 0.02 0.37" rgba="0.12 0.12 0.12 1"/>
      <geom type="box" pos="-0.55 0.25 0.37" size="0.02 0.02 0.37" rgba="0.12 0.12 0.12 1"/>
      <geom type="box" pos="0.55 -0.25 0.37" size="0.02 0.02 0.37" rgba="0.12 0.12 0.12 1"/>
      <geom type="box" pos="0.55 0.25 0.37" size="0.02 0.02 0.37" rgba="0.12 0.12 0.12 1"/>
      <geom type="box" pos="0.1 0 0.86" size="0.16 0.02 0.1" rgba="0.04 0.04 0.05 1"/>
    </body>
    <body pos="2.7 -2.4 0"><geom type="cylinder" pos="0 0 0.6" size="0.16 0.02" rgba="0.2 0.2 0.22 1"/><geom type="cylinder" pos="0 0 0.3" size="0.025 0.3" rgba="0.3 0.3 0.32 1"/></body>
    <body pos="3.2 -1.2 0" euler="0 0 3.1416">
      <geom type="box" pos="0 0 0.74" size="0.6 0.3 0.02" rgba="0.85 0.82 0.78 1"/>
      <geom type="box" pos="-0.55 -0.25 0.37" size="0.02 0.02 0.37" rgba="0.12 0.12 0.12 1"/>
      <geom type="box" pos="-0.55 0.25 0.37" size="0.02 0.02 0.37" rgba="0.12 0.12 0.12 1"/>
      <geom type="box" pos="0.55 -0.25 0.37" size="0.02 0.02 0.37" rgba="0.12 0.12 0.12 1"/>
      <geom type="box" pos="0.55 0.25 0.37" size="0.02 0.02 0.37" rgba="0.12 0.12 0.12 1"/>
      <geom type="box" pos="0.1 0 0.86" size="0.16 0.02 0.1" rgba="0.04 0.04 0.05 1"/>
    </body>
    <body pos="2.6500000000000004 -0.6499999999999999 0" euler="0 0 6.2832">
      <geom type="box" pos="0 0 1.0" size="0.16 0.11 0.22" rgba="0.4 0.3 0.1 1"/>
      <geom type="sphere" pos="0 0 1.32" size="0.1" rgba="0.82 0.66 0.54 1"/>
      <geom type="box" pos="0.36 -0.08 0.4" size="0.07 0.06 0.4" rgba="0.1 0.1 0.12 1"/>
      <geom type="box" pos="0.36 0.08 0.4" size="0.07 0.06 0.4" rgba="0.1 0.1 0.12 1"/>
    </body>
    <body pos="3.2 0 0" euler="0 0 3.1416">
      <geom type="box" pos="0 0 0.74" size="0.6 0.3 0.02" rgba="0.6 0.45 0.3 1"/>
      <geom type="box" pos="-0.55 -0.25 0.37" size="0.02 0.02 0.37" rgba="0.12 0.12 0.12 1"/>
      <geom type="box" pos="-0.55 0.25 0.37" size="0.02 0.02 0.37" rgba="0.12 0.12 0.12 1"/>
      <geom type="box" pos="0.55 -0.25 0.37" size="0.02 0.02 0.37" rgba="0.12 0.12 0.12 1"/>
      <geom type="box" pos="0.55 0.25 0.37" size="0.02 0.02 0.37" rgba="0.12 0.12 0.12 1"/>
      <geom type="box" pos="0.1 0 0.86" size="0.16 0.02 0.1" rgba="0.04 0.04 0.05 1"/>
    </body>
    <body pos="2.7 0 0"><geom type="cylinder" pos="0 0 0.6" size="0.16 0.02" rgba="0.2 0.2 0.22 1"/><geom type="cylinder" pos="0 0 0.3" size="0.025 0.3" rgba="0.3 0.3 0.32 1"/></body>
    <body pos="3.2 1.2 0" euler="0 0 3.1416">
      <geom type="box" pos="0 0 0.74" size="0.6 0.3 0.02" rgba="0.75 0.76 0.8 1"/>
      <geom type="box" pos="-0.55 -0.25 0.37" size="0.02 0.02 0.37" rgba="0.12 0.12 0.12 1"/>
      <geom type="box" pos="-0.55 0.25 0.37" size="0.02 0.02 0.37" rgba="0.12 0.12 0.12 1"/>
      <geom type="box" pos="0.55 -0.25 0.37" size="0.02 0.02 0.37" rgba="0.12 0.12 0.12 1"/>
      <geom type="box" pos="0.55 0.25 0.37" size="0.02 0.02 0.37" rgba="0.12 0.12 0.12 1"/>
      <geom type="box" pos="0.1 0 0.86" size="0.16 0.02 0.1" rgba="0.04 0.04 0.05 1"/>
    </body>
    <body pos="2.6500000000000004 0.6499999999999999 0" euler="0 0 6.2832">
      <geom type="box" pos="0 0 1.0" size="0.16 0.11 0.22" rgba="0.15 0.2 0.45 1"/>
      <geom type="sphere" pos="0 0 1.32" size="0.1" rgba="0.82 0.66 0.54 1"/>
      <geom type="box" pos="0.36 -0.08 0.4" size="0.07 0.06 0.4" rgba="0.1 0.1 0.12 1"/>
      <geom type="box" pos="0.36 0.08 0.4" size="0.07 0.06 0.4" rgba="0.1 0.1 0.12 1"/>
    </body>
    <body pos="3.2 2.4 0" euler="0 0 3.1416">
      <geom type="box" pos="0 0 0.74" size="0.6 0.3 0.02" rgba="0.85 0.82 0.78 1"/>
      <geom type="box" pos="-0.55 -0.25 0.37" size="0.02 0.02 0.37" rgba="0.12 0.12 0.12 1"/>
      <geom type="box" pos="-0.55 0.25 0.37" size="0.02 0.02 0.37" rgba="0.12 0.12 0.12 1"/>
      <geom type="box" pos="0.55 -0.25 0.37" size="0.02 0.02 0.37" rgba="0.12 0.12 0.12 1"/>
      <geom type="box" pos="0.55 0.25 0.37" size="0.02 0.02 0.37" rgba="0.12 0.12 0.12 1"/>
      <geom type="box" pos="0.1 0 0.86" size="0.16 0.02 0.1" rgba="0.04 0.04 0.05 1"/>
    </body>
    <body pos="2.7 2.4 0"><geom type="cylinder" pos="0 0 0.6" size="0.16 0.02" rgba="0.2 0.2 0.22 1"/><geom type="cylinder" pos="0 0 0.3" size="0.025 0.3" rgba="0.3 0.3 0.32 1"/></body>
    <body pos="-2 3.2 0" euler="0 0 -1.5708">
      <geom type="box" pos="0 0 0.74" size="0.6 0.3 0.02" rgba="0.6 0.45 0.3 1"/>
      <geom type="box" pos="-0.55 -0.25 0.37" size="0.02 0.02 0.37" rgba="0.12 0.12 0.12 1"/>
      <geom type="box" pos="-0.55 0.25 0.37" size="0.02 0.02 0.37" rgba="0.12 0.12 0.12 1"/>
      <geom type="box" pos="0.55 -0.25 0.37" size="0.02 0.02 0.37" rgba="0.12 0.12 0.12 1"/>
      <geom type="box" pos="0.55 0.25 0.37" size="0.02 0.02 0.37" rgba="0.12 0.12 0.12 1"/>
      <geom type="box" pos="0.1 0 0.86" size="0.16 0.02 0.1" rgba="0.04 0.04 0.05 1"/>
    </body>
    <body pos="-1.45 2.6500000000000004 0" euler="0 0 1.5708">
      <geom type="box" pos="0 0 1.0" size="0.16 0.11 0.22" rgba="0.2 0.2 0.22 1"/>
      <geom type="sphere" pos="0 0 1.32" size="0.1" rgba="0.82 0.66 0.54 1"/>
      <geom type="box" pos="0.36 -0.08 0.4" size="0.07 0.06 0.4" rgba="0.1 0.1 0.12 1"/>
      <geom type="box" pos="0.36 0.08 0.4" size="0.07 0.06 0.4" rgba="0.1 0.1 0.12 1"/>
    </body>
    <body pos="-0.7 3.2 0" euler="0 0 -1.5708">
      <geom type="box" pos="0 0 0.74" size="0.6 0.3 0.02" rgba="0.75 0.76 0.8 1"/>
      <geom type="box" pos="-0.55 -0.25 0.37" size="0.02 0.02 0.37" rgba="0.12 0.12 0.12 1"/>
      <geom type="box" pos="-0.55 0.25 0.37" size="0.02 0.02 0.37" rgba="0.12 0.12 0.12 1"/>
      <geom type="box" pos="0.55 -0.25 0.37" size="0.02 0.02 0.37" rgba="0.12 0.12 0.12 1"/>
      <geom type="box" pos="0.55 0.25 0.37" size="0.02 0.02 0.37" rgba="0.12 0.12 0.12 1"/>
      <geom type="box" pos="0.1 0 0.86" size="0.16 0.02 0.1" rgba="0.04 0.04 0.05 1"/>
    </body>
    <body pos="-0.19999999999999996 3.2 0"><geom type="cylinder" pos="0 0 0.6" size="0.16 0.02" rgba="0.2 0.2 0.22 1"/><geom type="cylinder" pos="0 0 0.3" size="0.025 0.3" rgba="0.3 0.3 0.32 1"/></body>
    <body pos="0.7 3.2 0" euler="0 0 -1.5708">
      <geom type="box" pos="0 0 0.74" size="0.6 0.3 0.02" rgba="0.85 0.82 0.78 1"/>
      <geom type="box" pos="-0.55 -0.25 0.37" size="0.02 0.02 0.37" rgba="0.12 0.12 0.12 1"/>
      <geom type="box" pos="-0.55 0.25 0.37" size="0.02 0.02 0.37" rgba="0.12 0.12 0.12 1"/>
      <geom type="box" pos="0.55 -0.25 0.37" size="0.02 0.02 0.37" rgba="0.12 0.12 0.12 1"/>
      <geom type="box" pos="0.55 0.25 0.37" size="0.02 0.02 0.37" rgba="0.12 0.12 0.12 1"/>
      <geom type="box" pos="0.1 0 0.86" size="0.16 0.02 0.1" rgba="0.04 0.04 0.05 1"/>
    </body>
    <body pos="0.1499999999999999 2.6500000000000004 0" euler="0 0 1.5708">
      <geom type="box" pos="0 0 1.0" size="0.16 0.11 0.22" rgba="0.35 0.35 0.4 1"/>
      <geom type="sphere" pos="0 0 1.32" size="0.1" rgba="0.82 0.66 0.54 1"/>
      <geom type="box" pos="0.36 -0.08 0.4" size="0.07 0.06 0.4" rgba="0.1 0.1 0.12 1"/>
      <geom type="box" pos="0.36 0.08 0.4" size="0.07 0.06 0.4" rgba="0.1 0.1 0.12 1"/>
    </body>
    <body pos="2 3.2 0" euler="0 0 -1.5708">
      <geom type="box" pos="0 0 0.74" size="0.6 0.3 0.02" rgba="0.6 0.45 0.3 1"/>
      <geom type="box" pos="-0.55 -0.25 0.37" size="0.02 0.02 0.37" rgba="0.12 0.12 0.12 1"/>
      <geom type="box" pos="-0.55 0.25 0.37" size="0.02 0.02 0.37" rgba="0.12 0.12 0.12 1"/>
      <geom type="box" pos="0.55 -0.25 0.37" size="0.02 0.02 0.37" rgba="0.12 0.12 0.12 1"/>
      <geom type="box" pos="0.55 0.25 0.37" size="0.02 0.02 0.37" rgba="0.12 0.12 0.12 1"/>
      <geom type="box" pos="0.1 0 0.86" size="0.16 0.02 0.1" rgba="0.04 0.04 0.05 1"/>
    </body>
    <body pos="1.5 3.2 0"><geom type="cylinder" pos="0 0 0.6" size="0.16 0.02" rgba="0.2 0.2 0.22 1"/><geom type="cylinder" pos="0 0 0.3" size="0.025 0.3" rgba="0.3 0.3 0.32 1"/></body>
    <body pos="-2 -3.2 0" euler="0 0 1.5708">
      <geom type="box" pos="0 0 0.74" size="0.6 0.3 0.02" rgba="0.75 0.76 0.8 1"/>
      <geom type="box" pos="-0.55 -0.25 0.37" size="0.02 0.02 0.37" rgba="0.12 0.12 0.12 1"/>
      <geom type="box" pos="-0.55 0.25 0.37" size="0.02 0.02 0.37" rgba="0.12 0.12 0.12 1"/>
      <geom type="box" pos="0.55 -0.25 0.37" size="0.02 0.02 0.37" rgba="0.12 0.12 0.12 1"/>
      <geom type="box" pos="0.55 0.25 0.37" size="0.02 0.02 0.37" rgba="0.12 0.12 0.12 1"/>
      <geom type="box" pos="0.1 0 0.86" size="0.16 0.02 0.1" rgba="0.04 0.04 0.05 1"/>
    </body>
    <body pos="-1.45 -2.6500000000000004 0" euler="0 0 4.7124">
      <geom type="box" pos="0 0 1.0" size="0.16 0.11 0.22" rgba="0.1 0.1 0.12 1"/>
      <geom type="sphere" pos="0 0 1.32" size="0.1" rgba="0.82 0.66 0.54 1"/>
      <geom type="box" pos="0.36 -0.08 0.4" size="0.07 0.06 0.4" rgba="0.1 0.1 0.12 1"/>
      <geom type="box" pos="0.36 0.08 0.4" size="0.07 0.06 0.4" rgba="0.1 0.1 0.12 1"/>
    </body>
    <body pos="-0.7 -3.2 0" euler="0 0 1.5708">
      <geom type="box" pos="0 0 0.74" size="0.6 0.3 0.02" rgba="0.85 0.82 0.78 1"/>
      <geom type="box" pos="-0.55 -0.25 0.37" size="0.02 0.02 0.37" rgba="0.12 0.12 0.12 1"/>
      <geom type="box" pos="-0.55 0.25 0.37" size="0.02 0.02 0.37" rgba="0.12 0.12 0.12 1"/>
      <geom type="box" pos="0.55 -0.25 0.37" size="0.02 0.02 0.37" rgba="0.12 0.12 0.12 1"/>
      <geom type="box" pos="0.55 0.25 0.37" size="0.02 0.02 0.37" rgba="0.12 0.12 0.12 1"/>
      <geom type="box" pos="0.1 0 0.86" size="0.16 0.02 0.1" rgba="0.04 0.04 0.05 1"/>
    </body>
    <body pos="-0.19999999999999996 -3.2 0"><geom type="cylinder" pos="0 0 0.6" size="0.16 0.02" rgba="0.2 0.2 0.22 1"/><geom type="cylinder" pos="0 0 0.3" size="0.025 0.3" rgba="0.3 0.3 0.32 1"/></body>
    <body pos="0.7 -3.2 0" euler="0 0 1.5708">
      <geom type="box" pos="0 0 0.74" size="0.6 0.3 0.02" rgba="0.6 0.45 0.3 1"/>
      <geom type="box" pos="-0.55 -0.25 0.37" size="0.02 0.02 0.37" rgba="0.12 0.12 0.12 1"/>
      <geom type="box" pos="-0.55 0.25 0.37" size="0.02 0.02 0.37" rgba="0.12 0.12 0.12 1"/>
      <geom type="box" pos="0.55 -0.25 0.37" size="0.02 0.02 0.37" rgba="0.12 0.12 0.12 1"/>
      <geom type="box" pos="0.55 0.25 0.37" size="0.02 0.02 0.37" rgba="0.12 0.12 0.12 1"/>
      <geom type="box" pos="0.1 0 0.86" size="0.16 0.02 0.1" rgba="0.04 0.04 0.05 1"/>
    </body>
    <body pos="0.1499999999999999 -2.6500000000000004 0" euler="0 0 4.7124">
      <geom type="box" pos="0 0 1.0" size="0.16 0.11 0.22" rgba="0.5 0.12 0.12 1"/>
      <geom type="sphere" pos="0 0 1.32" size="0.1" rgba="0.82 0.66 0.54 1"/>
      <geom type="box" pos="0.36 -0.08 0.4" size="0.07 0.06 0.4" rgba="0.1 0.1 0.12 1"/>
      <geom type="box" pos="0.36 0.08 0.4" size="0.07 0.06 0.4" rgba="0.1 0.1 0.12 1"/>
    </body>
    <body pos="2 -3.2 0" euler="0 0 1.5708">
      <geom type="box" pos="0 0 0.74" size="0.6 0.3 0.02" rgba="0.75 0.76 0.8 1"/>
      <geom type="box" pos="-0.55 -0.25 0.37" size="0.02 0.02 0.37" rgba="0.12 0.12 0.12 1"/>
      <geom type="box" pos="-0.55 0.25 0.37" size="0.02 0.02 0.37" rgba="0.12 0.12 0.12 1"/>
      <geom type="box" pos="0.55 -0.25 0.37" size="0.02 0.02 0.37" rgba="0.12 0.12 0.12 1"/>
      <geom type="box" pos="0.55 0.25 0.37" size="0.02 0.02 0.37" rgba="0.12 0.12 0.12 1"/>
      <geom type="box" pos="0.1 0 0.86" size="0.16 0.02 0.1" rgba="0.04 0.04 0.05 1"/>
    </body>
    <body pos="1.5 -3.2 0"><geom type="cylinder" pos="0 0 0.6" size="0.16 0.02" rgba="0.2 0.2 0.22 1"/><geom type="cylinder" pos="0 0 0.3" size="0.025 0.3" rgba="0.3 0.3 0.32 1"/></body>
    <body pos="0 -2.6 0" euler="0 0 1.5708">
      <geom type="box" pos="0 0 1.05" size="0.16 0.11 0.22" rgba="0.5 0.12 0.12 1"/>
      <geom type="sphere" pos="0 0 1.37" size="0.1" rgba="0.82 0.66 0.54 1"/>
      <geom type="box" pos="0.36 -0.08 0.4" size="0.07 0.06 0.4" rgba="0.1 0.1 0.12 1"/>
      <geom type="box" pos="0.36 0.08 0.4" size="0.07 0.06 0.4" rgba="0.1 0.1 0.12 1"/>
    </body>
    <body pos="-2.5 0 0" euler="0 0 0">
      <geom type="box" pos="0 0 1.05" size="0.16 0.11 0.22" rgba="0.15 0.2 0.45 1"/>
      <geom type="sphere" pos="0 0 1.37" size="0.1" rgba="0.82 0.66 0.54 1"/>
      <geom type="box" pos="0.36 -0.08 0.4" size="0.07 0.06 0.4" rgba="0.1 0.1 0.12 1"/>
      <geom type="box" pos="0.36 0.08 0.4" size="0.07 0.06 0.4" rgba="0.1 0.1 0.12 1"/>
    </body>
    <geom name="start_l" type="box" pos="1.153 0.044 0.05" size="0.015 0.015 0.05" rgba="0.1 0.9 0.2 1" contype="0" conaffinity="0"/>
    <geom name="start_r" type="box" pos="1.584 -0.044 0.05" size="0.015 0.015 0.05" rgba="0.1 0.9 0.2 1" contype="0" conaffinity="0"/>
    <geom type="box" pos="1.373 0.022 0.001" euler="0 0 1.368" size="0.035 0.200 0.001" rgba="0.22 0.22 0.25 1" contype="0" conaffinity="0"/>
    <geom type="box" pos="1.380 0.065 0.001" euler="0 0 1.429" size="0.035 0.200 0.001" rgba="0.22 0.22 0.25 1" contype="0" conaffinity="0"/>
    <geom type="box" pos="1.385 0.109 0.001" euler="0 0 1.498" size="0.035 0.200 0.001" rgba="0.22 0.22 0.25 1" contype="0" conaffinity="0"/>
    <geom type="box" pos="1.387 0.153 0.001" euler="0 0 1.574" size="0.035 0.200 0.001" rgba="0.22 0.22 0.25 1" contype="0" conaffinity="0"/>
    <geom type="box" pos="1.385 0.197 0.001" euler="0 0 1.655" size="0.035 0.200 0.001" rgba="0.22 0.22 0.25 1" contype="0" conaffinity="0"/>
    <geom type="box" pos="1.379 0.241 0.001" euler="0 0 1.741" size="0.035 0.200 0.001" rgba="0.22 0.22 0.25 1" contype="0" conaffinity="0"/>
    <geom type="box" pos="1.370 0.284 0.001" euler="0 0 1.831" size="0.035 0.200 0.001" rgba="0.22 0.22 0.25 1" contype="0" conaffinity="0"/>
    <geom type="box" pos="1.356 0.326 0.001" euler="0 0 1.922" size="0.035 0.200 0.001" rgba="0.22 0.22 0.25 1" contype="0" conaffinity="0"/>
    <geom type="box" pos="1.339 0.366 0.001" euler="0 0 2.015" size="0.035 0.200 0.001" rgba="0.22 0.22 0.25 1" contype="0" conaffinity="0"/>
    <geom type="box" pos="1.319 0.406 0.001" euler="0 0 2.106" size="0.036 0.200 0.001" rgba="0.22 0.22 0.25 1" contype="0" conaffinity="0"/>
    <geom type="box" pos="1.294 0.443 0.001" euler="0 0 2.195" size="0.036 0.200 0.001" rgba="0.22 0.22 0.25 1" contype="0" conaffinity="0"/>
    <geom type="box" pos="1.266 0.478 0.001" euler="0 0 2.281" size="0.036 0.200 0.001" rgba="0.22 0.22 0.25 1" contype="0" conaffinity="0"/>
    <geom type="box" pos="1.235 0.511 0.001" euler="0 0 2.362" size="0.036 0.200 0.001" rgba="0.22 0.22 0.25 1" contype="0" conaffinity="0"/>
    <geom type="box" pos="1.202 0.542 0.001" euler="0 0 2.438" size="0.037 0.200 0.001" rgba="0.22 0.22 0.25 1" contype="0" conaffinity="0"/>
    <geom type="box" pos="1.165 0.571 0.001" euler="0 0 2.509" size="0.037 0.200 0.001" rgba="0.22 0.22 0.25 1" contype="0" conaffinity="0"/>
    <geom type="box" pos="1.127 0.597 0.001" euler="0 0 2.573" size="0.037 0.200 0.001" rgba="0.22 0.22 0.25 1" contype="0" conaffinity="0"/>
    <geom type="box" pos="1.088 0.620 0.001" euler="0 0 2.632" size="0.037 0.200 0.001" rgba="0.22 0.22 0.25 1" contype="0" conaffinity="0"/>
    <geom type="box" pos="1.047 0.642 0.001" euler="0 0 2.684" size="0.037 0.200 0.001" rgba="0.22 0.22 0.25 1" contype="0" conaffinity="0"/>
    <geom type="box" pos="1.006 0.661 0.001" euler="0 0 2.729" size="0.036 0.200 0.001" rgba="0.22 0.22 0.25 1" contype="0" conaffinity="0"/>
    <geom type="box" pos="0.965 0.678 0.001" euler="0 0 2.767" size="0.036 0.200 0.001" rgba="0.22 0.22 0.25 1" contype="0" conaffinity="0"/>
    <geom type="box" pos="0.924 0.693 0.001" euler="0 0 2.799" size="0.035 0.200 0.001" rgba="0.22 0.22 0.25 1" contype="0" conaffinity="0"/>
    <geom type="box" pos="0.883 0.707 0.001" euler="0 0 2.823" size="0.034 0.200 0.001" rgba="0.22 0.22 0.25 1" contype="0" conaffinity="0"/>
    <geom type="box" pos="0.843 0.720 0.001" euler="0 0 2.840" size="0.033 0.200 0.001" rgba="0.22 0.22 0.25 1" contype="0" conaffinity="0"/>
    <geom type="box" pos="0.805 0.732 0.001" euler="0 0 2.849" size="0.032 0.200 0.001" rgba="0.22 0.22 0.25 1" contype="0" conaffinity="0"/>
    <geom type="box" pos="0.767 0.743 0.001" euler="0 0 2.850" size="0.031 0.200 0.001" rgba="0.22 0.22 0.25 1" contype="0" conaffinity="0"/>
    <geom type="box" pos="0.731 0.754 0.001" euler="0 0 2.843" size="0.030 0.200 0.001" rgba="0.22 0.22 0.25 1" contype="0" conaffinity="0"/>
    <geom type="box" pos="0.696 0.765 0.001" euler="0 0 2.829" size="0.029 0.200 0.001" rgba="0.22 0.22 0.25 1" contype="0" conaffinity="0"/>
    <geom type="box" pos="0.663 0.776 0.001" euler="0 0 2.807" size="0.028 0.200 0.001" rgba="0.22 0.22 0.25 1" contype="0" conaffinity="0"/>
    <geom type="box" pos="0.631 0.788 0.001" euler="0 0 2.779" size="0.027 0.200 0.001" rgba="0.22 0.22 0.25 1" contype="0" conaffinity="0"/>
    <geom type="box" pos="0.601 0.800 0.001" euler="0 0 2.747" size="0.026 0.200 0.001" rgba="0.22 0.22 0.25 1" contype="0" conaffinity="0"/>
    <geom type="box" pos="0.571 0.813 0.001" euler="0 0 2.712" size="0.025 0.200 0.001" rgba="0.22 0.22 0.25 1" contype="0" conaffinity="0"/>
    <geom type="box" pos="0.543 0.826 0.001" euler="0 0 2.677" size="0.025 0.200 0.001" rgba="0.22 0.22 0.25 1" contype="0" conaffinity="0"/>
    <geom type="box" pos="0.515 0.841 0.001" euler="0 0 2.645" size="0.025 0.200 0.001" rgba="0.22 0.22 0.25 1" contype="0" conaffinity="0"/>
    <geom type="box" pos="0.488 0.856 0.001" euler="0 0 2.617" size="0.025 0.200 0.001" rgba="0.22 0.22 0.25 1" contype="0" conaffinity="0"/>
    <geom type="box" pos="0.462 0.872 0.001" euler="0 0 2.596" size="0.025 0.200 0.001" rgba="0.22 0.22 0.25 1" contype="0" conaffinity="0"/>
    <geom type="box" pos="0.435 0.888 0.001" euler="0 0 2.583" size="0.025 0.200 0.001" rgba="0.22 0.22 0.25 1" contype="0" conaffinity="0"/>
    <geom type="box" pos="0.409 0.905 0.001" euler="0 0 2.577" size="0.025 0.200 0.001" rgba="0.22 0.22 0.25 1" contype="0" conaffinity="0"/>
    <geom type="box" pos="0.382 0.922 0.001" euler="0 0 2.581" size="0.025 0.200 0.001" rgba="0.22 0.22 0.25 1" contype="0" conaffinity="0"/>
    <geom type="box" pos="0.355 0.939 0.001" euler="0 0 2.592" size="0.026 0.200 0.001" rgba="0.22 0.22 0.25 1" contype="0" conaffinity="0"/>
    <geom type="box" pos="0.327 0.955 0.001" euler="0 0 2.610" size="0.026 0.200 0.001" rgba="0.22 0.22 0.25 1" contype="0" conaffinity="0"/>
    <geom type="box" pos="0.299 0.971 0.001" euler="0 0 2.636" size="0.026 0.200 0.001" rgba="0.22 0.22 0.25 1" contype="0" conaffinity="0"/>
    <geom type="box" pos="0.270 0.987 0.001" euler="0 0 2.667" size="0.026 0.200 0.001" rgba="0.22 0.22 0.25 1" contype="0" conaffinity="0"/>
    <geom type="box" pos="0.240 1.001 0.001" euler="0 0 2.703" size="0.026 0.200 0.001" rgba="0.22 0.22 0.25 1" contype="0" conaffinity="0"/>
    <geom type="box" pos="0.210 1.015 0.001" euler="0 0 2.742" size="0.027 0.200 0.001" rgba="0.22 0.22 0.25 1" contype="0" conaffinity="0"/>
    <geom type="box" pos="0.179 1.027 0.001" euler="0 0 2.784" size="0.027 0.200 0.001" rgba="0.22 0.22 0.25 1" contype="0" conaffinity="0"/>
    <geom type="box" pos="0.148 1.038 0.001" euler="0 0 2.827" size="0.027 0.200 0.001" rgba="0.22 0.22 0.25 1" contype="0" conaffinity="0"/>
    <geom type="box" pos="0.116 1.048 0.001" euler="0 0 2.869" size="0.027 0.200 0.001" rgba="0.22 0.22 0.25 1" contype="0" conaffinity="0"/>
    <geom type="box" pos="0.083 1.056 0.001" euler="0 0 2.911" size="0.027 0.200 0.001" rgba="0.22 0.22 0.25 1" contype="0" conaffinity="0"/>
    <geom type="box" pos="0.050 1.063 0.001" euler="0 0 2.950" size="0.027 0.200 0.001" rgba="0.22 0.22 0.25 1" contype="0" conaffinity="0"/>
    <geom type="box" pos="0.017 1.069 0.001" euler="0 0 2.985" size="0.027 0.200 0.001" rgba="0.22 0.22 0.25 1" contype="0" conaffinity="0"/>
    <geom type="box" pos="-0.017 1.074 0.001" euler="0 0 3.016" size="0.027 0.200 0.001" rgba="0.22 0.22 0.25 1" contype="0" conaffinity="0"/>
    <geom type="box" pos="-0.051 1.078 0.001" euler="0 0 3.042" size="0.027 0.200 0.001" rgba="0.22 0.22 0.25 1" contype="0" conaffinity="0"/>
    <geom type="box" pos="-0.085 1.081 0.001" euler="0 0 3.062" size="0.028 0.200 0.001" rgba="0.22 0.22 0.25 1" contype="0" conaffinity="0"/>
    <geom type="box" pos="-0.120 1.083 0.001" euler="0 0 3.076" size="0.028 0.200 0.001" rgba="0.22 0.22 0.25 1" contype="0" conaffinity="0"/>
    <geom type="box" pos="-0.155 1.085 0.001" euler="0 0 3.084" size="0.028 0.200 0.001" rgba="0.22 0.22 0.25 1" contype="0" conaffinity="0"/>
    <geom type="box" pos="-0.190 1.087 0.001" euler="0 0 3.088" size="0.028 0.200 0.001" rgba="0.22 0.22 0.25 1" contype="0" conaffinity="0"/>
    <geom type="box" pos="-0.226 1.089 0.001" euler="0 0 3.086" size="0.029 0.200 0.001" rgba="0.22 0.22 0.25 1" contype="0" conaffinity="0"/>
    <geom type="box" pos="-0.262 1.091 0.001" euler="0 0 3.082" size="0.029 0.200 0.001" rgba="0.22 0.22 0.25 1" contype="0" conaffinity="0"/>
    <geom type="box" pos="-0.299 1.094 0.001" euler="0 0 3.075" size="0.030 0.200 0.001" rgba="0.22 0.22 0.25 1" contype="0" conaffinity="0"/>
    <geom type="box" pos="-0.337 1.096 0.001" euler="0 0 3.068" size="0.031 0.200 0.001" rgba="0.22 0.22 0.25 1" contype="0" conaffinity="0"/>
    <geom type="box" pos="-0.377 1.099 0.001" euler="0 0 3.062" size="0.032 0.200 0.001" rgba="0.22 0.22 0.25 1" contype="0" conaffinity="0"/>
    <geom type="box" pos="-0.417 1.103 0.001" euler="0 0 3.058" size="0.033 0.200 0.001" rgba="0.22 0.22 0.25 1" contype="0" conaffinity="0"/>
    <geom type="box" pos="-0.458 1.106 0.001" euler="0 0 3.058" size="0.034 0.200 0.001" rgba="0.22 0.22 0.25 1" contype="0" conaffinity="0"/>
    <geom type="box" pos="-0.501 1.110 0.001" euler="0 0 3.062" size="0.035 0.200 0.001" rgba="0.22 0.22 0.25 1" contype="0" conaffinity="0"/>
    <geom type="box" pos="-0.545 1.113 0.001" euler="0 0 3.071" size="0.036 0.200 0.001" rgba="0.22 0.22 0.25 1" contype="0" conaffinity="0"/>
    <geom type="box" pos="-0.591 1.116 0.001" euler="0 0 3.086" size="0.037 0.200 0.001" rgba="0.22 0.22 0.25 1" contype="0" conaffinity="0"/>
    <geom type="box" pos="-0.638 1.118 0.001" euler="0 0 3.108" size="0.038 0.200 0.001" rgba="0.22 0.22 0.25 1" contype="0" conaffinity="0"/>
    <geom type="box" pos="-0.686 1.119 0.001" euler="0 0 3.136" size="0.039 0.200 0.001" rgba="0.22 0.22 0.25 1" contype="0" conaffinity="0"/>
    <geom type="box" pos="-0.735 1.118 0.001" euler="0 0 -3.113" size="0.040 0.200 0.001" rgba="0.22 0.22 0.25 1" contype="0" conaffinity="0"/>
    <geom type="box" pos="-0.784 1.116 0.001" euler="0 0 -3.071" size="0.040 0.200 0.001" rgba="0.22 0.22 0.25 1" contype="0" conaffinity="0"/>
    <geom type="box" pos="-0.834 1.111 0.001" euler="0 0 -3.021" size="0.040 0.200 0.001" rgba="0.22 0.22 0.25 1" contype="0" conaffinity="0"/>
    <geom type="box" pos="-0.884 1.104 0.001" euler="0 0 -2.964" size="0.040 0.200 0.001" rgba="0.22 0.22 0.25 1" contype="0" conaffinity="0"/>
    <geom type="box" pos="-0.934 1.093 0.001" euler="0 0 -2.898" size="0.040 0.200 0.001" rgba="0.22 0.22 0.25 1" contype="0" conaffinity="0"/>
    <geom type="box" pos="-0.982 1.079 0.001" euler="0 0 -2.824" size="0.040 0.200 0.001" rgba="0.22 0.22 0.25 1" contype="0" conaffinity="0"/>
    <geom type="box" pos="-1.029 1.061 0.001" euler="0 0 -2.740" size="0.040 0.200 0.001" rgba="0.22 0.22 0.25 1" contype="0" conaffinity="0"/>
    <geom type="box" pos="-1.073 1.040 0.001" euler="0 0 -2.647" size="0.039 0.200 0.001" rgba="0.22 0.22 0.25 1" contype="0" conaffinity="0"/>
    <geom type="box" pos="-1.115 1.015 0.001" euler="0 0 -2.545" size="0.039 0.200 0.001" rgba="0.22 0.22 0.25 1" contype="0" conaffinity="0"/>
    <geom type="box" pos="-1.154 0.985 0.001" euler="0 0 -2.433" size="0.039 0.200 0.001" rgba="0.22 0.22 0.25 1" contype="0" conaffinity="0"/>
    <geom type="box" pos="-1.188 0.952 0.001" euler="0 0 -2.314" size="0.038 0.200 0.001" rgba="0.22 0.22 0.25 1" contype="0" conaffinity="0"/>
    <geom type="box" pos="-1.218 0.915 0.001" euler="0 0 -2.188" size="0.038 0.200 0.001" rgba="0.22 0.22 0.25 1" contype="0" conaffinity="0"/>
    <geom type="box" pos="-1.243 0.874 0.001" euler="0 0 -2.058" size="0.039 0.200 0.001" rgba="0.22 0.22 0.25 1" contype="0" conaffinity="0"/>
    <geom type="box" pos="-1.263 0.830 0.001" euler="0 0 -1.928" size="0.039 0.200 0.001" rgba="0.22 0.22 0.25 1" contype="0" conaffinity="0"/>
    <geom type="box" pos="-1.277 0.783 0.001" euler="0 0 -1.799" size="0.040 0.200 0.001" rgba="0.22 0.22 0.25 1" contype="0" conaffinity="0"/>
    <geom type="box" pos="-1.286 0.733 0.001" euler="0 0 -1.675" size="0.041 0.200 0.001" rgba="0.22 0.22 0.25 1" contype="0" conaffinity="0"/>
    <geom type="box" pos="-1.288 0.682 0.001" euler="0 0 -1.557" size="0.042 0.200 0.001" rgba="0.22 0.22 0.25 1" contype="0" conaffinity="0"/>
    <geom type="box" pos="-1.284 0.629 0.001" euler="0 0 -1.447" size="0.043 0.200 0.001" rgba="0.22 0.22 0.25 1" contype="0" conaffinity="0"/>
    <geom type="box" pos="-1.275 0.576 0.001" euler="0 0 -1.345" size="0.044 0.200 0.001" rgba="0.22 0.22 0.25 1" contype="0" conaffinity="0"/>
    <geom type="box" pos="-1.260 0.522 0.001" euler="0 0 -1.253" size="0.045 0.200 0.001" rgba="0.22 0.22 0.25 1" contype="0" conaffinity="0"/>
    <geom type="box" pos="-1.239 0.469 0.001" euler="0 0 -1.169" size="0.046 0.200 0.001" rgba="0.22 0.22 0.25 1" contype="0" conaffinity="0"/>
    <geom type="box" pos="-1.215 0.416 0.001" euler="0 0 -1.093" size="0.047 0.200 0.001" rgba="0.22 0.22 0.25 1" contype="0" conaffinity="0"/>
    <geom type="box" pos="-1.186 0.365 0.001" euler="0 0 -1.025" size="0.047 0.200 0.001" rgba="0.22 0.22 0.25 1" contype="0" conaffinity="0"/>
    <geom type="box" pos="-1.154 0.316 0.001" euler="0 0 -0.966" size="0.047 0.200 0.001" rgba="0.22 0.22 0.25 1" contype="0" conaffinity="0"/>
    <geom type="box" pos="-1.120 0.269 0.001" euler="0 0 -0.914" size="0.046 0.200 0.001" rgba="0.22 0.22 0.25 1" contype="0" conaffinity="0"/>
    <geom type="box" pos="-1.084 0.225 0.001" euler="0 0 -0.871" size="0.045 0.200 0.001" rgba="0.22 0.22 0.25 1" contype="0" conaffinity="0"/>
    <geom type="box" pos="-1.048 0.183 0.001" euler="0 0 -0.836" size="0.043 0.200 0.001" rgba="0.22 0.22 0.25 1" contype="0" conaffinity="0"/>
    <geom type="box" pos="-1.012 0.144 0.001" euler="0 0 -0.812" size="0.041 0.200 0.001" rgba="0.22 0.22 0.25 1" contype="0" conaffinity="0"/>
    <geom type="box" pos="-0.977 0.108 0.001" euler="0 0 -0.801" size="0.039 0.200 0.001" rgba="0.22 0.22 0.25 1" contype="0" conaffinity="0"/>
    <geom type="box" pos="-0.945 0.075 0.001" euler="0 0 -0.804" size="0.036 0.200 0.001" rgba="0.22 0.22 0.25 1" contype="0" conaffinity="0"/>
    <geom type="box" pos="-0.916 0.043 0.001" euler="0 0 -0.828" size="0.033 0.200 0.001" rgba="0.22 0.22 0.25 1" contype="0" conaffinity="0"/>
    <geom type="box" pos="-0.890 0.014 0.001" euler="0 0 -0.879" size="0.029 0.200 0.001" rgba="0.22 0.22 0.25 1" contype="0" conaffinity="0"/>
    <geom type="box" pos="-0.869 -0.014 0.001" euler="0 0 -0.965" size="0.026 0.200 0.001" rgba="0.22 0.22 0.25 1" contype="0" conaffinity="0"/>
    <geom type="box" pos="-0.853 -0.040 0.001" euler="0 0 -1.097" size="0.024 0.200 0.001" rgba="0.22 0.22 0.25 1" contype="0" conaffinity="0"/>
    <geom type="box" pos="-0.842 -0.066 0.001" euler="0 0 -1.278" size="0.022 0.200 0.001" rgba="0.22 0.22 0.25 1" contype="0" conaffinity="0"/>
    <geom type="box" pos="-0.837 -0.092 0.001" euler="0 0 -1.492" size="0.021 0.200 0.001" rgba="0.22 0.22 0.25 1" contype="0" conaffinity="0"/>
    <geom type="box" pos="-0.838 -0.119 0.001" euler="0 0 -1.705" size="0.022 0.200 0.001" rgba="0.22 0.22 0.25 1" contype="0" conaffinity="0"/>
    <geom type="box" pos="-0.844 -0.148 0.001" euler="0 0 -1.882" size="0.024 0.200 0.001" rgba="0.22 0.22 0.25 1" contype="0" conaffinity="0"/>
    <geom type="box" pos="-0.856 -0.178 0.001" euler="0 0 -2.010" size="0.027 0.200 0.001" rgba="0.22 0.22 0.25 1" contype="0" conaffinity="0"/>
    <geom type="box" pos="-0.873 -0.210 0.001" euler="0 0 -2.094" size="0.031 0.200 0.001" rgba="0.22 0.22 0.25 1" contype="0" conaffinity="0"/>
    <geom type="box" pos="-0.895 -0.245 0.001" euler="0 0 -2.144" size="0.035 0.200 0.001" rgba="0.22 0.22 0.25 1" contype="0" conaffinity="0"/>
    <geom type="box" pos="-0.920 -0.283 0.001" euler="0 0 -2.167" size="0.039 0.200 0.001" rgba="0.22 0.22 0.25 1" contype="0" conaffinity="0"/>
    <geom type="box" pos="-0.949 -0.325 0.001" euler="0 0 -2.171" size="0.042 0.200 0.001" rgba="0.22 0.22 0.25 1" contype="0" conaffinity="0"/>
    <geom type="box" pos="-0.980 -0.371 0.001" euler="0 0 -2.160" size="0.045 0.200 0.001" rgba="0.22 0.22 0.25 1" contype="0" conaffinity="0"/>
    <geom type="box" pos="-1.011 -0.419 0.001" euler="0 0 -2.137" size="0.048 0.200 0.001" rgba="0.22 0.22 0.25 1" contype="0" conaffinity="0"/>
    <geom type="box" pos="-1.043 -0.471 0.001" euler="0 0 -2.104" size="0.050 0.200 0.001" rgba="0.22 0.22 0.25 1" contype="0" conaffinity="0"/>
    <geom type="box" pos="-1.074 -0.527 0.001" euler="0 0 -2.063" size="0.052 0.200 0.001" rgba="0.22 0.22 0.25 1" contype="0" conaffinity="0"/>
    <geom type="box" pos="-1.104 -0.585 0.001" euler="0 0 -2.012" size="0.052 0.200 0.001" rgba="0.22 0.22 0.25 1" contype="0" conaffinity="0"/>
    <geom type="box" pos="-1.130 -0.645 0.001" euler="0 0 -1.954" size="0.053 0.200 0.001" rgba="0.22 0.22 0.25 1" contype="0" conaffinity="0"/>
    <geom type="box" pos="-1.152 -0.707 0.001" euler="0 0 -1.887" size="0.052 0.200 0.001" rgba="0.22 0.22 0.25 1" contype="0" conaffinity="0"/>
    <geom type="box" pos="-1.170 -0.769 0.001" euler="0 0 -1.810" size="0.052 0.200 0.001" rgba="0.22 0.22 0.25 1" contype="0" conaffinity="0"/>
    <geom type="box" pos="-1.183 -0.832 0.001" euler="0 0 -1.723" size="0.050 0.200 0.001" rgba="0.22 0.22 0.25 1" contype="0" conaffinity="0"/>
    <geom type="box" pos="-1.189 -0.893 0.001" euler="0 0 -1.625" size="0.049 0.200 0.001" rgba="0.22 0.22 0.25 1" contype="0" conaffinity="0"/>
    <geom type="box" pos="-1.189 -0.953 0.001" euler="0 0 -1.514" size="0.047 0.200 0.001" rgba="0.22 0.22 0.25 1" contype="0" conaffinity="0"/>
    <geom type="box" pos="-1.182 -1.010 0.001" euler="0 0 -1.388" size="0.045 0.200 0.001" rgba="0.22 0.22 0.25 1" contype="0" conaffinity="0"/>
    <geom type="box" pos="-1.169 -1.063 0.001" euler="0 0 -1.247" size="0.043 0.200 0.001" rgba="0.22 0.22 0.25 1" contype="0" conaffinity="0"/>
    <geom type="box" pos="-1.148 -1.112 0.001" euler="0 0 -1.093" size="0.042 0.200 0.001" rgba="0.22 0.22 0.25 1" contype="0" conaffinity="0"/>
    <geom type="box" pos="-1.120 -1.156 0.001" euler="0 0 -0.926" size="0.041 0.200 0.001" rgba="0.22 0.22 0.25 1" contype="0" conaffinity="0"/>
    <geom type="box" pos="-1.087 -1.194 0.001" euler="0 0 -0.753" size="0.041 0.200 0.001" rgba="0.22 0.22 0.25 1" contype="0" conaffinity="0"/>
    <geom type="box" pos="-1.047 -1.225 0.001" euler="0 0 -0.579" size="0.041 0.200 0.001" rgba="0.22 0.22 0.25 1" contype="0" conaffinity="0"/>
    <geom type="box" pos="-1.001 -1.250 0.001" euler="0 0 -0.410" size="0.042 0.200 0.001" rgba="0.22 0.22 0.25 1" contype="0" conaffinity="0"/>
    <geom type="box" pos="-0.951 -1.267 0.001" euler="0 0 -0.252" size="0.043 0.200 0.001" rgba="0.22 0.22 0.25 1" contype="0" conaffinity="0"/>
    <geom type="box" pos="-0.897 -1.276 0.001" euler="0 0 -0.107" size="0.045 0.200 0.001" rgba="0.22 0.22 0.25 1" contype="0" conaffinity="0"/>
    <geom type="box" pos="-0.840 -1.279 0.001" euler="0 0 0.023" size="0.047 0.200 0.001" rgba="0.22 0.22 0.25 1" contype="0" conaffinity="0"/>
    <geom type="box" pos="-0.781 -1.274 0.001" euler="0 0 0.139" size="0.049 0.200 0.001" rgba="0.22 0.22 0.25 1" contype="0" conaffinity="0"/>
    <geom type="box" pos="-0.720 -1.262 0.001" euler="0 0 0.241" size="0.050 0.200 0.001" rgba="0.22 0.22 0.25 1" contype="0" conaffinity="0"/>
    <geom type="box" pos="-0.659 -1.244 0.001" euler="0 0 0.332" size="0.052 0.200 0.001" rgba="0.22 0.22 0.25 1" contype="0" conaffinity="0"/>
    <geom type="box" pos="-0.598 -1.220 0.001" euler="0 0 0.412" size="0.053 0.200 0.001" rgba="0.22 0.22 0.25 1" contype="0" conaffinity="0"/>
    <geom type="box" pos="-0.538 -1.192 0.001" euler="0 0 0.484" size="0.053 0.200 0.001" rgba="0.22 0.22 0.25 1" contype="0" conaffinity="0"/>
    <geom type="box" pos="-0.480 -1.159 0.001" euler="0 0 0.546" size="0.053 0.200 0.001" rgba="0.22 0.22 0.25 1" contype="0" conaffinity="0"/>
    <geom type="box" pos="-0.425 -1.123 0.001" euler="0 0 0.601" size="0.053 0.200 0.001" rgba="0.22 0.22 0.25 1" contype="0" conaffinity="0"/>
    <geom type="box" pos="-0.372 -1.085 0.001" euler="0 0 0.649" size="0.052 0.200 0.001" rgba="0.22 0.22 0.25 1" contype="0" conaffinity="0"/>
    <geom type="box" pos="-0.322 -1.045 0.001" euler="0 0 0.688" size="0.050 0.200 0.001" rgba="0.22 0.22 0.25 1" contype="0" conaffinity="0"/>
    <geom type="box" pos="-0.276 -1.006 0.001" euler="0 0 0.720" size="0.048 0.200 0.001" rgba="0.22 0.22 0.25 1" contype="0" conaffinity="0"/>
    <geom type="box" pos="-0.233 -0.967 0.001" euler="0 0 0.742" size="0.045 0.200 0.001" rgba="0.22 0.22 0.25 1" contype="0" conaffinity="0"/>
    <geom type="box" pos="-0.193 -0.931 0.001" euler="0 0 0.752" size="0.041 0.200 0.001" rgba="0.22 0.22 0.25 1" contype="0" conaffinity="0"/>
    <geom type="box" pos="-0.157 -0.897 0.001" euler="0 0 0.749" size="0.038 0.200 0.001" rgba="0.22 0.22 0.25 1" contype="0" conaffinity="0"/>
    <geom type="box" pos="-0.124 -0.867 0.001" euler="0 0 0.728" size="0.034 0.200 0.001" rgba="0.22 0.22 0.25 1" contype="0" conaffinity="0"/>
    <geom type="box" pos="-0.093 -0.841 0.001" euler="0 0 0.683" size="0.030 0.200 0.001" rgba="0.22 0.22 0.25 1" contype="0" conaffinity="0"/>
    <geom type="box" pos="-0.065 -0.819 0.001" euler="0 0 0.605" size="0.027 0.200 0.001" rgba="0.22 0.22 0.25 1" contype="0" conaffinity="0"/>
    <geom type="box" pos="-0.038 -0.803 0.001" euler="0 0 0.485" size="0.023 0.200 0.001" rgba="0.22 0.22 0.25 1" contype="0" conaffinity="0"/>
    <geom type="box" pos="-0.013 -0.792 0.001" euler="0 0 0.318" size="0.021 0.200 0.001" rgba="0.22 0.22 0.25 1" contype="0" conaffinity="0"/>
    <geom type="box" pos="0.012 -0.786 0.001" euler="0 0 0.114" size="0.020 0.200 0.001" rgba="0.22 0.22 0.25 1" contype="0" conaffinity="0"/>
    <geom type="box" pos="0.037 -0.786 0.001" euler="0 0 -0.098" size="0.020 0.200 0.001" rgba="0.22 0.22 0.25 1" contype="0" conaffinity="0"/>
    <geom type="box" pos="0.062 -0.791 0.001" euler="0 0 -0.282" size="0.021 0.200 0.001" rgba="0.22 0.22 0.25 1" contype="0" conaffinity="0"/>
    <geom type="box" pos="0.089 -0.801 0.001" euler="0 0 -0.419" size="0.023 0.200 0.001" rgba="0.22 0.22 0.25 1" contype="0" conaffinity="0"/>
    <geom type="box" pos="0.116 -0.815 0.001" euler="0 0 -0.511" size="0.026 0.200 0.001" rgba="0.22 0.22 0.25 1" contype="0" conaffinity="0"/>
    <geom type="box" pos="0.145 -0.832 0.001" euler="0 0 -0.566" size="0.029 0.200 0.001" rgba="0.22 0.22 0.25 1" contype="0" conaffinity="0"/>
    <geom type="box" pos="0.177 -0.853 0.001" euler="0 0 -0.593" size="0.031 0.200 0.001" rgba="0.22 0.22 0.25 1" contype="0" conaffinity="0"/>
    <geom type="box" pos="0.210 -0.876 0.001" euler="0 0 -0.598" size="0.034 0.200 0.001" rgba="0.22 0.22 0.25 1" contype="0" conaffinity="0"/>
    <geom type="box" pos="0.246 -0.900 0.001" euler="0 0 -0.587" size="0.036 0.200 0.001" rgba="0.22 0.22 0.25 1" contype="0" conaffinity="0"/>
    <geom type="box" pos="0.285 -0.925 0.001" euler="0 0 -0.562" size="0.037 0.200 0.001" rgba="0.22 0.22 0.25 1" contype="0" conaffinity="0"/>
    <geom type="box" pos="0.325 -0.949 0.001" euler="0 0 -0.527" size="0.039 0.200 0.001" rgba="0.22 0.22 0.25 1" contype="0" conaffinity="0"/>
    <geom type="box" pos="0.368 -0.973 0.001" euler="0 0 -0.483" size="0.039 0.200 0.001" rgba="0.22 0.22 0.25 1" contype="0" conaffinity="0"/>
    <geom type="box" pos="0.412 -0.994 0.001" euler="0 0 -0.429" size="0.040 0.200 0.001" rgba="0.22 0.22 0.25 1" contype="0" conaffinity="0"/>
    <geom type="box" pos="0.458 -1.014 0.001" euler="0 0 -0.368" size="0.040 0.200 0.001" rgba="0.22 0.22 0.25 1" contype="0" conaffinity="0"/>
    <geom type="box" pos="0.505 -1.030 0.001" euler="0 0 -0.298" size="0.040 0.200 0.001" rgba="0.22 0.22 0.25 1" contype="0" conaffinity="0"/>
    <geom type="box" pos="0.552 -1.043 0.001" euler="0 0 -0.221" size="0.039 0.200 0.001" rgba="0.22 0.22 0.25 1" contype="0" conaffinity="0"/>
    <geom type="box" pos="0.600 -1.051 0.001" euler="0 0 -0.136" size="0.038 0.200 0.001" rgba="0.22 0.22 0.25 1" contype="0" conaffinity="0"/>
    <geom type="box" pos="0.647 -1.055 0.001" euler="0 0 -0.044" size="0.038 0.200 0.001" rgba="0.22 0.22 0.25 1" contype="0" conaffinity="0"/>
    <geom type="box" pos="0.693 -1.055 0.001" euler="0 0 0.054" size="0.037 0.200 0.001" rgba="0.22 0.22 0.25 1" contype="0" conaffinity="0"/>
    <geom type="box" pos="0.738 -1.050 0.001" euler="0 0 0.158" size="0.036 0.200 0.001" rgba="0.22 0.22 0.25 1" contype="0" conaffinity="0"/>
    <geom type="box" pos="0.782 -1.041 0.001" euler="0 0 0.266" size="0.035 0.200 0.001" rgba="0.22 0.22 0.25 1" contype="0" conaffinity="0"/>
    <geom type="box" pos="0.823 -1.027 0.001" euler="0 0 0.377" size="0.035 0.200 0.001" rgba="0.22 0.22 0.25 1" contype="0" conaffinity="0"/>
    <geom type="box" pos="0.862 -1.009 0.001" euler="0 0 0.487" size="0.034 0.200 0.001" rgba="0.22 0.22 0.25 1" contype="0" conaffinity="0"/>
    <geom type="box" pos="0.899 -0.988 0.001" euler="0 0 0.595" size="0.034 0.200 0.001" rgba="0.22 0.22 0.25 1" contype="0" conaffinity="0"/>
    <geom type="box" pos="0.932 -0.962 0.001" euler="0 0 0.698" size="0.034 0.200 0.001" rgba="0.22 0.22 0.25 1" contype="0" conaffinity="0"/>
    <geom type="box" pos="0.963 -0.934 0.001" euler="0 0 0.794" size="0.034 0.200 0.001" rgba="0.22 0.22 0.25 1" contype="0" conaffinity="0"/>
    <geom type="box" pos="0.992 -0.902 0.001" euler="0 0 0.883" size="0.034 0.200 0.001" rgba="0.22 0.22 0.25 1" contype="0" conaffinity="0"/>
    <geom type="box" pos="1.017 -0.869 0.001" euler="0 0 0.961" size="0.034 0.200 0.001" rgba="0.22 0.22 0.25 1" contype="0" conaffinity="0"/>
    <geom type="box" pos="1.040 -0.833 0.001" euler="0 0 1.030" size="0.034 0.200 0.001" rgba="0.22 0.22 0.25 1" contype="0" conaffinity="0"/>
    <geom type="box" pos="1.061 -0.796 0.001" euler="0 0 1.089" size="0.034 0.200 0.001" rgba="0.22 0.22 0.25 1" contype="0" conaffinity="0"/>
    <geom type="box" pos="1.079 -0.759 0.001" euler="0 0 1.138" size="0.034 0.200 0.001" rgba="0.22 0.22 0.25 1" contype="0" conaffinity="0"/>
    <geom type="box" pos="1.096 -0.720 0.001" euler="0 0 1.176" size="0.034 0.200 0.001" rgba="0.22 0.22 0.25 1" contype="0" conaffinity="0"/>
    <geom type="box" pos="1.112 -0.681 0.001" euler="0 0 1.204" size="0.033 0.200 0.001" rgba="0.22 0.22 0.25 1" contype="0" conaffinity="0"/>
    <geom type="box" pos="1.126 -0.642 0.001" euler="0 0 1.223" size="0.033 0.200 0.001" rgba="0.22 0.22 0.25 1" contype="0" conaffinity="0"/>
    <geom type="box" pos="1.140 -0.604 0.001" euler="0 0 1.233" size="0.033 0.200 0.001" rgba="0.22 0.22 0.25 1" contype="0" conaffinity="0"/>
    <geom type="box" pos="1.153 -0.565 0.001" euler="0 0 1.235" size="0.033 0.200 0.001" rgba="0.22 0.22 0.25 1" contype="0" conaffinity="0"/>
    <geom type="box" pos="1.167 -0.527 0.001" euler="0 0 1.231" size="0.032 0.200 0.001" rgba="0.22 0.22 0.25 1" contype="0" conaffinity="0"/>
    <geom type="box" pos="1.180 -0.489 0.001" euler="0 0 1.221" size="0.032 0.200 0.001" rgba="0.22 0.22 0.25 1" contype="0" conaffinity="0"/>
    <geom type="box" pos="1.194 -0.451 0.001" euler="0 0 1.208" size="0.032 0.200 0.001" rgba="0.22 0.22 0.25 1" contype="0" conaffinity="0"/>
    <geom type="box" pos="1.209 -0.414 0.001" euler="0 0 1.193" size="0.032 0.200 0.001" rgba="0.22 0.22 0.25 1" contype="0" conaffinity="0"/>
    <geom type="box" pos="1.224 -0.377 0.001" euler="0 0 1.179" size="0.032 0.200 0.001" rgba="0.22 0.22 0.25 1" contype="0" conaffinity="0"/>
    <geom type="box" pos="1.240 -0.339 0.001" euler="0 0 1.168" size="0.033 0.200 0.001" rgba="0.22 0.22 0.25 1" contype="0" conaffinity="0"/>
    <geom type="box" pos="1.256 -0.301 0.001" euler="0 0 1.161" size="0.033 0.200 0.001" rgba="0.22 0.22 0.25 1" contype="0" conaffinity="0"/>
    <geom type="box" pos="1.273 -0.263 0.001" euler="0 0 1.160" size="0.033 0.200 0.001" rgba="0.22 0.22 0.25 1" contype="0" conaffinity="0"/>
    <geom type="box" pos="1.289 -0.225 0.001" euler="0 0 1.166" size="0.034 0.200 0.001" rgba="0.22 0.22 0.25 1" contype="0" conaffinity="0"/>
    <geom type="box" pos="1.306 -0.186 0.001" euler="0 0 1.179" size="0.034 0.200 0.001" rgba="0.22 0.22 0.25 1" contype="0" conaffinity="0"/>
    <geom type="box" pos="1.322 -0.146 0.001" euler="0 0 1.201" size="0.035 0.200 0.001" rgba="0.22 0.22 0.25 1" contype="0" conaffinity="0"/>
    <geom type="box" pos="1.337 -0.105 0.001" euler="0 0 1.230" size="0.035 0.200 0.001" rgba="0.22 0.22 0.25 1" contype="0" conaffinity="0"/>
    <geom type="box" pos="1.351 -0.064 0.001" euler="0 0 1.268" size="0.035 0.200 0.001" rgba="0.22 0.22 0.25 1" contype="0" conaffinity="0"/>
    <geom type="box" pos="1.363 -0.021 0.001" euler="0 0 1.314" size="0.035 0.200 0.001" rgba="0.22 0.22 0.25 1" contype="0" conaffinity="0"/>
    <geom type="box" pos="1.373 0.022 0.0025" euler="0 0 1.368" size="0.035 0.022 0.0012" rgba="0.95 0.85 0.05 1" contype="0" conaffinity="0"/>
    <geom type="box" pos="1.380 0.065 0.0025" euler="0 0 1.429" size="0.035 0.022 0.0012" rgba="0.95 0.85 0.05 1" contype="0" conaffinity="0"/>
    <geom type="box" pos="1.385 0.109 0.0025" euler="0 0 1.498" size="0.035 0.022 0.0012" rgba="0.95 0.85 0.05 1" contype="0" conaffinity="0"/>
    <geom type="box" pos="1.387 0.153 0.0025" euler="0 0 1.574" size="0.035 0.022 0.0012" rgba="0.95 0.85 0.05 1" contype="0" conaffinity="0"/>
    <geom type="box" pos="1.385 0.197 0.0025" euler="0 0 1.655" size="0.035 0.022 0.0012" rgba="0.95 0.85 0.05 1" contype="0" conaffinity="0"/>
    <geom type="box" pos="1.379 0.241 0.0025" euler="0 0 1.741" size="0.035 0.022 0.0012" rgba="0.95 0.85 0.05 1" contype="0" conaffinity="0"/>
    <geom type="box" pos="1.370 0.284 0.0025" euler="0 0 1.831" size="0.035 0.022 0.0012" rgba="0.95 0.85 0.05 1" contype="0" conaffinity="0"/>
    <geom type="box" pos="1.356 0.326 0.0025" euler="0 0 1.922" size="0.035 0.022 0.0012" rgba="0.95 0.85 0.05 1" contype="0" conaffinity="0"/>
    <geom type="box" pos="1.339 0.366 0.0025" euler="0 0 2.015" size="0.035 0.022 0.0012" rgba="0.95 0.85 0.05 1" contype="0" conaffinity="0"/>
    <geom type="box" pos="1.319 0.406 0.0025" euler="0 0 2.106" size="0.036 0.022 0.0012" rgba="0.95 0.85 0.05 1" contype="0" conaffinity="0"/>
    <geom type="box" pos="1.294 0.443 0.0025" euler="0 0 2.195" size="0.036 0.022 0.0012" rgba="0.95 0.85 0.05 1" contype="0" conaffinity="0"/>
    <geom type="box" pos="1.266 0.478 0.0025" euler="0 0 2.281" size="0.036 0.022 0.0012" rgba="0.95 0.85 0.05 1" contype="0" conaffinity="0"/>
    <geom type="box" pos="1.235 0.511 0.0025" euler="0 0 2.362" size="0.036 0.022 0.0012" rgba="0.95 0.85 0.05 1" contype="0" conaffinity="0"/>
    <geom type="box" pos="1.202 0.542 0.0025" euler="0 0 2.438" size="0.037 0.022 0.0012" rgba="0.95 0.85 0.05 1" contype="0" conaffinity="0"/>
    <geom type="box" pos="1.165 0.571 0.0025" euler="0 0 2.509" size="0.037 0.022 0.0012" rgba="0.95 0.85 0.05 1" contype="0" conaffinity="0"/>
    <geom type="box" pos="1.127 0.597 0.0025" euler="0 0 2.573" size="0.037 0.022 0.0012" rgba="0.95 0.85 0.05 1" contype="0" conaffinity="0"/>
    <geom type="box" pos="1.088 0.620 0.0025" euler="0 0 2.632" size="0.037 0.022 0.0012" rgba="0.95 0.85 0.05 1" contype="0" conaffinity="0"/>
    <geom type="box" pos="1.047 0.642 0.0025" euler="0 0 2.684" size="0.037 0.022 0.0012" rgba="0.95 0.85 0.05 1" contype="0" conaffinity="0"/>
    <geom type="box" pos="1.006 0.661 0.0025" euler="0 0 2.729" size="0.036 0.022 0.0012" rgba="0.95 0.85 0.05 1" contype="0" conaffinity="0"/>
    <geom type="box" pos="0.965 0.678 0.0025" euler="0 0 2.767" size="0.036 0.022 0.0012" rgba="0.95 0.85 0.05 1" contype="0" conaffinity="0"/>
    <geom type="box" pos="0.924 0.693 0.0025" euler="0 0 2.799" size="0.035 0.022 0.0012" rgba="0.95 0.85 0.05 1" contype="0" conaffinity="0"/>
    <geom type="box" pos="0.883 0.707 0.0025" euler="0 0 2.823" size="0.034 0.022 0.0012" rgba="0.95 0.85 0.05 1" contype="0" conaffinity="0"/>
    <geom type="box" pos="0.843 0.720 0.0025" euler="0 0 2.840" size="0.033 0.022 0.0012" rgba="0.95 0.85 0.05 1" contype="0" conaffinity="0"/>
    <geom type="box" pos="0.805 0.732 0.0025" euler="0 0 2.849" size="0.032 0.022 0.0012" rgba="0.95 0.85 0.05 1" contype="0" conaffinity="0"/>
    <geom type="box" pos="0.767 0.743 0.0025" euler="0 0 2.850" size="0.031 0.022 0.0012" rgba="0.95 0.85 0.05 1" contype="0" conaffinity="0"/>
    <geom type="box" pos="0.731 0.754 0.0025" euler="0 0 2.843" size="0.030 0.022 0.0012" rgba="0.95 0.85 0.05 1" contype="0" conaffinity="0"/>
    <geom type="box" pos="0.696 0.765 0.0025" euler="0 0 2.829" size="0.029 0.022 0.0012" rgba="0.95 0.85 0.05 1" contype="0" conaffinity="0"/>
    <geom type="box" pos="0.663 0.776 0.0025" euler="0 0 2.807" size="0.028 0.022 0.0012" rgba="0.95 0.85 0.05 1" contype="0" conaffinity="0"/>
    <geom type="box" pos="0.631 0.788 0.0025" euler="0 0 2.779" size="0.027 0.022 0.0012" rgba="0.95 0.85 0.05 1" contype="0" conaffinity="0"/>
    <geom type="box" pos="0.601 0.800 0.0025" euler="0 0 2.747" size="0.026 0.022 0.0012" rgba="0.95 0.85 0.05 1" contype="0" conaffinity="0"/>
    <geom type="box" pos="0.571 0.813 0.0025" euler="0 0 2.712" size="0.025 0.022 0.0012" rgba="0.95 0.85 0.05 1" contype="0" conaffinity="0"/>
    <geom type="box" pos="0.543 0.826 0.0025" euler="0 0 2.677" size="0.025 0.022 0.0012" rgba="0.95 0.85 0.05 1" contype="0" conaffinity="0"/>
    <geom type="box" pos="0.515 0.841 0.0025" euler="0 0 2.645" size="0.025 0.022 0.0012" rgba="0.95 0.85 0.05 1" contype="0" conaffinity="0"/>
    <geom type="box" pos="0.488 0.856 0.0025" euler="0 0 2.617" size="0.025 0.022 0.0012" rgba="0.95 0.85 0.05 1" contype="0" conaffinity="0"/>
    <geom type="box" pos="0.462 0.872 0.0025" euler="0 0 2.596" size="0.025 0.022 0.0012" rgba="0.95 0.85 0.05 1" contype="0" conaffinity="0"/>
    <geom type="box" pos="0.435 0.888 0.0025" euler="0 0 2.583" size="0.025 0.022 0.0012" rgba="0.95 0.85 0.05 1" contype="0" conaffinity="0"/>
    <geom type="box" pos="0.409 0.905 0.0025" euler="0 0 2.577" size="0.025 0.022 0.0012" rgba="0.95 0.85 0.05 1" contype="0" conaffinity="0"/>
    <geom type="box" pos="0.382 0.922 0.0025" euler="0 0 2.581" size="0.025 0.022 0.0012" rgba="0.95 0.85 0.05 1" contype="0" conaffinity="0"/>
    <geom type="box" pos="0.355 0.939 0.0025" euler="0 0 2.592" size="0.026 0.022 0.0012" rgba="0.95 0.85 0.05 1" contype="0" conaffinity="0"/>
    <geom type="box" pos="0.327 0.955 0.0025" euler="0 0 2.610" size="0.026 0.022 0.0012" rgba="0.95 0.85 0.05 1" contype="0" conaffinity="0"/>
    <geom type="box" pos="0.299 0.971 0.0025" euler="0 0 2.636" size="0.026 0.022 0.0012" rgba="0.95 0.85 0.05 1" contype="0" conaffinity="0"/>
    <geom type="box" pos="0.270 0.987 0.0025" euler="0 0 2.667" size="0.026 0.022 0.0012" rgba="0.95 0.85 0.05 1" contype="0" conaffinity="0"/>
    <geom type="box" pos="0.240 1.001 0.0025" euler="0 0 2.703" size="0.026 0.022 0.0012" rgba="0.95 0.85 0.05 1" contype="0" conaffinity="0"/>
    <geom type="box" pos="0.210 1.015 0.0025" euler="0 0 2.742" size="0.027 0.022 0.0012" rgba="0.95 0.85 0.05 1" contype="0" conaffinity="0"/>
    <geom type="box" pos="0.179 1.027 0.0025" euler="0 0 2.784" size="0.027 0.022 0.0012" rgba="0.95 0.85 0.05 1" contype="0" conaffinity="0"/>
    <geom type="box" pos="0.148 1.038 0.0025" euler="0 0 2.827" size="0.027 0.022 0.0012" rgba="0.95 0.85 0.05 1" contype="0" conaffinity="0"/>
    <geom type="box" pos="0.116 1.048 0.0025" euler="0 0 2.869" size="0.027 0.022 0.0012" rgba="0.95 0.85 0.05 1" contype="0" conaffinity="0"/>
    <geom type="box" pos="0.083 1.056 0.0025" euler="0 0 2.911" size="0.027 0.022 0.0012" rgba="0.95 0.85 0.05 1" contype="0" conaffinity="0"/>
    <geom type="box" pos="0.050 1.063 0.0025" euler="0 0 2.950" size="0.027 0.022 0.0012" rgba="0.95 0.85 0.05 1" contype="0" conaffinity="0"/>
    <geom type="box" pos="0.017 1.069 0.0025" euler="0 0 2.985" size="0.027 0.022 0.0012" rgba="0.95 0.85 0.05 1" contype="0" conaffinity="0"/>
    <geom type="box" pos="-0.017 1.074 0.0025" euler="0 0 3.016" size="0.027 0.022 0.0012" rgba="0.95 0.85 0.05 1" contype="0" conaffinity="0"/>
    <geom type="box" pos="-0.051 1.078 0.0025" euler="0 0 3.042" size="0.027 0.022 0.0012" rgba="0.95 0.85 0.05 1" contype="0" conaffinity="0"/>
    <geom type="box" pos="-0.085 1.081 0.0025" euler="0 0 3.062" size="0.028 0.022 0.0012" rgba="0.95 0.85 0.05 1" contype="0" conaffinity="0"/>
    <geom type="box" pos="-0.120 1.083 0.0025" euler="0 0 3.076" size="0.028 0.022 0.0012" rgba="0.95 0.85 0.05 1" contype="0" conaffinity="0"/>
    <geom type="box" pos="-0.155 1.085 0.0025" euler="0 0 3.084" size="0.028 0.022 0.0012" rgba="0.95 0.85 0.05 1" contype="0" conaffinity="0"/>
    <geom type="box" pos="-0.190 1.087 0.0025" euler="0 0 3.088" size="0.028 0.022 0.0012" rgba="0.95 0.85 0.05 1" contype="0" conaffinity="0"/>
    <geom type="box" pos="-0.226 1.089 0.0025" euler="0 0 3.086" size="0.029 0.022 0.0012" rgba="0.95 0.85 0.05 1" contype="0" conaffinity="0"/>
    <geom type="box" pos="-0.262 1.091 0.0025" euler="0 0 3.082" size="0.029 0.022 0.0012" rgba="0.95 0.85 0.05 1" contype="0" conaffinity="0"/>
    <geom type="box" pos="-0.299 1.094 0.0025" euler="0 0 3.075" size="0.030 0.022 0.0012" rgba="0.95 0.85 0.05 1" contype="0" conaffinity="0"/>
    <geom type="box" pos="-0.337 1.096 0.0025" euler="0 0 3.068" size="0.031 0.022 0.0012" rgba="0.95 0.85 0.05 1" contype="0" conaffinity="0"/>
    <geom type="box" pos="-0.377 1.099 0.0025" euler="0 0 3.062" size="0.032 0.022 0.0012" rgba="0.95 0.85 0.05 1" contype="0" conaffinity="0"/>
    <geom type="box" pos="-0.417 1.103 0.0025" euler="0 0 3.058" size="0.033 0.022 0.0012" rgba="0.95 0.85 0.05 1" contype="0" conaffinity="0"/>
    <geom type="box" pos="-0.458 1.106 0.0025" euler="0 0 3.058" size="0.034 0.022 0.0012" rgba="0.95 0.85 0.05 1" contype="0" conaffinity="0"/>
    <geom type="box" pos="-0.501 1.110 0.0025" euler="0 0 3.062" size="0.035 0.022 0.0012" rgba="0.95 0.85 0.05 1" contype="0" conaffinity="0"/>
    <geom type="box" pos="-0.545 1.113 0.0025" euler="0 0 3.071" size="0.036 0.022 0.0012" rgba="0.95 0.85 0.05 1" contype="0" conaffinity="0"/>
    <geom type="box" pos="-0.591 1.116 0.0025" euler="0 0 3.086" size="0.037 0.022 0.0012" rgba="0.95 0.85 0.05 1" contype="0" conaffinity="0"/>
    <geom type="box" pos="-0.638 1.118 0.0025" euler="0 0 3.108" size="0.038 0.022 0.0012" rgba="0.95 0.85 0.05 1" contype="0" conaffinity="0"/>
    <geom type="box" pos="-0.686 1.119 0.0025" euler="0 0 3.136" size="0.039 0.022 0.0012" rgba="0.95 0.85 0.05 1" contype="0" conaffinity="0"/>
    <geom type="box" pos="-0.735 1.118 0.0025" euler="0 0 -3.113" size="0.040 0.022 0.0012" rgba="0.95 0.85 0.05 1" contype="0" conaffinity="0"/>
    <geom type="box" pos="-0.784 1.116 0.0025" euler="0 0 -3.071" size="0.040 0.022 0.0012" rgba="0.95 0.85 0.05 1" contype="0" conaffinity="0"/>
    <geom type="box" pos="-0.834 1.111 0.0025" euler="0 0 -3.021" size="0.040 0.022 0.0012" rgba="0.95 0.85 0.05 1" contype="0" conaffinity="0"/>
    <geom type="box" pos="-0.884 1.104 0.0025" euler="0 0 -2.964" size="0.040 0.022 0.0012" rgba="0.95 0.85 0.05 1" contype="0" conaffinity="0"/>
    <geom type="box" pos="-0.934 1.093 0.0025" euler="0 0 -2.898" size="0.040 0.022 0.0012" rgba="0.95 0.85 0.05 1" contype="0" conaffinity="0"/>
    <geom type="box" pos="-0.982 1.079 0.0025" euler="0 0 -2.824" size="0.040 0.022 0.0012" rgba="0.95 0.85 0.05 1" contype="0" conaffinity="0"/>
    <geom type="box" pos="-1.029 1.061 0.0025" euler="0 0 -2.740" size="0.040 0.022 0.0012" rgba="0.95 0.85 0.05 1" contype="0" conaffinity="0"/>
    <geom type="box" pos="-1.073 1.040 0.0025" euler="0 0 -2.647" size="0.039 0.022 0.0012" rgba="0.95 0.85 0.05 1" contype="0" conaffinity="0"/>
    <geom type="box" pos="-1.115 1.015 0.0025" euler="0 0 -2.545" size="0.039 0.022 0.0012" rgba="0.95 0.85 0.05 1" contype="0" conaffinity="0"/>
    <geom type="box" pos="-1.154 0.985 0.0025" euler="0 0 -2.433" size="0.039 0.022 0.0012" rgba="0.95 0.85 0.05 1" contype="0" conaffinity="0"/>
    <geom type="box" pos="-1.188 0.952 0.0025" euler="0 0 -2.314" size="0.038 0.022 0.0012" rgba="0.95 0.85 0.05 1" contype="0" conaffinity="0"/>
    <geom type="box" pos="-1.218 0.915 0.0025" euler="0 0 -2.188" size="0.038 0.022 0.0012" rgba="0.95 0.85 0.05 1" contype="0" conaffinity="0"/>
    <geom type="box" pos="-1.243 0.874 0.0025" euler="0 0 -2.058" size="0.039 0.022 0.0012" rgba="0.95 0.85 0.05 1" contype="0" conaffinity="0"/>
    <geom type="box" pos="-1.263 0.830 0.0025" euler="0 0 -1.928" size="0.039 0.022 0.0012" rgba="0.95 0.85 0.05 1" contype="0" conaffinity="0"/>
    <geom type="box" pos="-1.277 0.783 0.0025" euler="0 0 -1.799" size="0.040 0.022 0.0012" rgba="0.95 0.85 0.05 1" contype="0" conaffinity="0"/>
    <geom type="box" pos="-1.286 0.733 0.0025" euler="0 0 -1.675" size="0.041 0.022 0.0012" rgba="0.95 0.85 0.05 1" contype="0" conaffinity="0"/>
    <geom type="box" pos="-1.288 0.682 0.0025" euler="0 0 -1.557" size="0.042 0.022 0.0012" rgba="0.95 0.85 0.05 1" contype="0" conaffinity="0"/>
    <geom type="box" pos="-1.284 0.629 0.0025" euler="0 0 -1.447" size="0.043 0.022 0.0012" rgba="0.95 0.85 0.05 1" contype="0" conaffinity="0"/>
    <geom type="box" pos="-1.275 0.576 0.0025" euler="0 0 -1.345" size="0.044 0.022 0.0012" rgba="0.95 0.85 0.05 1" contype="0" conaffinity="0"/>
    <geom type="box" pos="-1.260 0.522 0.0025" euler="0 0 -1.253" size="0.045 0.022 0.0012" rgba="0.95 0.85 0.05 1" contype="0" conaffinity="0"/>
    <geom type="box" pos="-1.239 0.469 0.0025" euler="0 0 -1.169" size="0.046 0.022 0.0012" rgba="0.95 0.85 0.05 1" contype="0" conaffinity="0"/>
    <geom type="box" pos="-1.215 0.416 0.0025" euler="0 0 -1.093" size="0.047 0.022 0.0012" rgba="0.95 0.85 0.05 1" contype="0" conaffinity="0"/>
    <geom type="box" pos="-1.186 0.365 0.0025" euler="0 0 -1.025" size="0.047 0.022 0.0012" rgba="0.95 0.85 0.05 1" contype="0" conaffinity="0"/>
    <geom type="box" pos="-1.154 0.316 0.0025" euler="0 0 -0.966" size="0.047 0.022 0.0012" rgba="0.95 0.85 0.05 1" contype="0" conaffinity="0"/>
    <geom type="box" pos="-1.120 0.269 0.0025" euler="0 0 -0.914" size="0.046 0.022 0.0012" rgba="0.95 0.85 0.05 1" contype="0" conaffinity="0"/>
    <geom type="box" pos="-1.084 0.225 0.0025" euler="0 0 -0.871" size="0.045 0.022 0.0012" rgba="0.95 0.85 0.05 1" contype="0" conaffinity="0"/>
    <geom type="box" pos="-1.048 0.183 0.0025" euler="0 0 -0.836" size="0.043 0.022 0.0012" rgba="0.95 0.85 0.05 1" contype="0" conaffinity="0"/>
    <geom type="box" pos="-1.012 0.144 0.0025" euler="0 0 -0.812" size="0.041 0.022 0.0012" rgba="0.95 0.85 0.05 1" contype="0" conaffinity="0"/>
    <geom type="box" pos="-0.977 0.108 0.0025" euler="0 0 -0.801" size="0.039 0.022 0.0012" rgba="0.95 0.85 0.05 1" contype="0" conaffinity="0"/>
    <geom type="box" pos="-0.945 0.075 0.0025" euler="0 0 -0.804" size="0.036 0.022 0.0012" rgba="0.95 0.85 0.05 1" contype="0" conaffinity="0"/>
    <geom type="box" pos="-0.916 0.043 0.0025" euler="0 0 -0.828" size="0.033 0.022 0.0012" rgba="0.95 0.85 0.05 1" contype="0" conaffinity="0"/>
    <geom type="box" pos="-0.890 0.014 0.0025" euler="0 0 -0.879" size="0.029 0.022 0.0012" rgba="0.95 0.85 0.05 1" contype="0" conaffinity="0"/>
    <geom type="box" pos="-0.869 -0.014 0.0025" euler="0 0 -0.965" size="0.026 0.022 0.0012" rgba="0.95 0.85 0.05 1" contype="0" conaffinity="0"/>
    <geom type="box" pos="-0.853 -0.040 0.0025" euler="0 0 -1.097" size="0.024 0.022 0.0012" rgba="0.95 0.85 0.05 1" contype="0" conaffinity="0"/>
    <geom type="box" pos="-0.842 -0.066 0.0025" euler="0 0 -1.278" size="0.022 0.022 0.0012" rgba="0.95 0.85 0.05 1" contype="0" conaffinity="0"/>
    <geom type="box" pos="-0.837 -0.092 0.0025" euler="0 0 -1.492" size="0.021 0.022 0.0012" rgba="0.95 0.85 0.05 1" contype="0" conaffinity="0"/>
    <geom type="box" pos="-0.838 -0.119 0.0025" euler="0 0 -1.705" size="0.022 0.022 0.0012" rgba="0.95 0.85 0.05 1" contype="0" conaffinity="0"/>
    <geom type="box" pos="-0.844 -0.148 0.0025" euler="0 0 -1.882" size="0.024 0.022 0.0012" rgba="0.95 0.85 0.05 1" contype="0" conaffinity="0"/>
    <geom type="box" pos="-0.856 -0.178 0.0025" euler="0 0 -2.010" size="0.027 0.022 0.0012" rgba="0.95 0.85 0.05 1" contype="0" conaffinity="0"/>
    <geom type="box" pos="-0.873 -0.210 0.0025" euler="0 0 -2.094" size="0.031 0.022 0.0012" rgba="0.95 0.85 0.05 1" contype="0" conaffinity="0"/>
    <geom type="box" pos="-0.895 -0.245 0.0025" euler="0 0 -2.144" size="0.035 0.022 0.0012" rgba="0.95 0.85 0.05 1" contype="0" conaffinity="0"/>
    <geom type="box" pos="-0.920 -0.283 0.0025" euler="0 0 -2.167" size="0.039 0.022 0.0012" rgba="0.95 0.85 0.05 1" contype="0" conaffinity="0"/>
    <geom type="box" pos="-0.949 -0.325 0.0025" euler="0 0 -2.171" size="0.042 0.022 0.0012" rgba="0.95 0.85 0.05 1" contype="0" conaffinity="0"/>
    <geom type="box" pos="-0.980 -0.371 0.0025" euler="0 0 -2.160" size="0.045 0.022 0.0012" rgba="0.95 0.85 0.05 1" contype="0" conaffinity="0"/>
    <geom type="box" pos="-1.011 -0.419 0.0025" euler="0 0 -2.137" size="0.048 0.022 0.0012" rgba="0.95 0.85 0.05 1" contype="0" conaffinity="0"/>
    <geom type="box" pos="-1.043 -0.471 0.0025" euler="0 0 -2.104" size="0.050 0.022 0.0012" rgba="0.95 0.85 0.05 1" contype="0" conaffinity="0"/>
    <geom type="box" pos="-1.074 -0.527 0.0025" euler="0 0 -2.063" size="0.052 0.022 0.0012" rgba="0.95 0.85 0.05 1" contype="0" conaffinity="0"/>
    <geom type="box" pos="-1.104 -0.585 0.0025" euler="0 0 -2.012" size="0.052 0.022 0.0012" rgba="0.95 0.85 0.05 1" contype="0" conaffinity="0"/>
    <geom type="box" pos="-1.130 -0.645 0.0025" euler="0 0 -1.954" size="0.053 0.022 0.0012" rgba="0.95 0.85 0.05 1" contype="0" conaffinity="0"/>
    <geom type="box" pos="-1.152 -0.707 0.0025" euler="0 0 -1.887" size="0.052 0.022 0.0012" rgba="0.95 0.85 0.05 1" contype="0" conaffinity="0"/>
    <geom type="box" pos="-1.170 -0.769 0.0025" euler="0 0 -1.810" size="0.052 0.022 0.0012" rgba="0.95 0.85 0.05 1" contype="0" conaffinity="0"/>
    <geom type="box" pos="-1.183 -0.832 0.0025" euler="0 0 -1.723" size="0.050 0.022 0.0012" rgba="0.95 0.85 0.05 1" contype="0" conaffinity="0"/>
    <geom type="box" pos="-1.189 -0.893 0.0025" euler="0 0 -1.625" size="0.049 0.022 0.0012" rgba="0.95 0.85 0.05 1" contype="0" conaffinity="0"/>
    <geom type="box" pos="-1.189 -0.953 0.0025" euler="0 0 -1.514" size="0.047 0.022 0.0012" rgba="0.95 0.85 0.05 1" contype="0" conaffinity="0"/>
    <geom type="box" pos="-1.182 -1.010 0.0025" euler="0 0 -1.388" size="0.045 0.022 0.0012" rgba="0.95 0.85 0.05 1" contype="0" conaffinity="0"/>
    <geom type="box" pos="-1.169 -1.063 0.0025" euler="0 0 -1.247" size="0.043 0.022 0.0012" rgba="0.95 0.85 0.05 1" contype="0" conaffinity="0"/>
    <geom type="box" pos="-1.148 -1.112 0.0025" euler="0 0 -1.093" size="0.042 0.022 0.0012" rgba="0.95 0.85 0.05 1" contype="0" conaffinity="0"/>
    <geom type="box" pos="-1.120 -1.156 0.0025" euler="0 0 -0.926" size="0.041 0.022 0.0012" rgba="0.95 0.85 0.05 1" contype="0" conaffinity="0"/>
    <geom type="box" pos="-1.087 -1.194 0.0025" euler="0 0 -0.753" size="0.041 0.022 0.0012" rgba="0.95 0.85 0.05 1" contype="0" conaffinity="0"/>
    <geom type="box" pos="-1.047 -1.225 0.0025" euler="0 0 -0.579" size="0.041 0.022 0.0012" rgba="0.95 0.85 0.05 1" contype="0" conaffinity="0"/>
    <geom type="box" pos="-1.001 -1.250 0.0025" euler="0 0 -0.410" size="0.042 0.022 0.0012" rgba="0.95 0.85 0.05 1" contype="0" conaffinity="0"/>
    <geom type="box" pos="-0.951 -1.267 0.0025" euler="0 0 -0.252" size="0.043 0.022 0.0012" rgba="0.95 0.85 0.05 1" contype="0" conaffinity="0"/>
    <geom type="box" pos="-0.897 -1.276 0.0025" euler="0 0 -0.107" size="0.045 0.022 0.0012" rgba="0.95 0.85 0.05 1" contype="0" conaffinity="0"/>
    <geom type="box" pos="-0.840 -1.279 0.0025" euler="0 0 0.023" size="0.047 0.022 0.0012" rgba="0.95 0.85 0.05 1" contype="0" conaffinity="0"/>
    <geom type="box" pos="-0.781 -1.274 0.0025" euler="0 0 0.139" size="0.049 0.022 0.0012" rgba="0.95 0.85 0.05 1" contype="0" conaffinity="0"/>
    <geom type="box" pos="-0.720 -1.262 0.0025" euler="0 0 0.241" size="0.050 0.022 0.0012" rgba="0.95 0.85 0.05 1" contype="0" conaffinity="0"/>
    <geom type="box" pos="-0.659 -1.244 0.0025" euler="0 0 0.332" size="0.052 0.022 0.0012" rgba="0.95 0.85 0.05 1" contype="0" conaffinity="0"/>
    <geom type="box" pos="-0.598 -1.220 0.0025" euler="0 0 0.412" size="0.053 0.022 0.0012" rgba="0.95 0.85 0.05 1" contype="0" conaffinity="0"/>
    <geom type="box" pos="-0.538 -1.192 0.0025" euler="0 0 0.484" size="0.053 0.022 0.0012" rgba="0.95 0.85 0.05 1" contype="0" conaffinity="0"/>
    <geom type="box" pos="-0.480 -1.159 0.0025" euler="0 0 0.546" size="0.053 0.022 0.0012" rgba="0.95 0.85 0.05 1" contype="0" conaffinity="0"/>
    <geom type="box" pos="-0.425 -1.123 0.0025" euler="0 0 0.601" size="0.053 0.022 0.0012" rgba="0.95 0.85 0.05 1" contype="0" conaffinity="0"/>
    <geom type="box" pos="-0.372 -1.085 0.0025" euler="0 0 0.649" size="0.052 0.022 0.0012" rgba="0.95 0.85 0.05 1" contype="0" conaffinity="0"/>
    <geom type="box" pos="-0.322 -1.045 0.0025" euler="0 0 0.688" size="0.050 0.022 0.0012" rgba="0.95 0.85 0.05 1" contype="0" conaffinity="0"/>
    <geom type="box" pos="-0.276 -1.006 0.0025" euler="0 0 0.720" size="0.048 0.022 0.0012" rgba="0.95 0.85 0.05 1" contype="0" conaffinity="0"/>
    <geom type="box" pos="-0.233 -0.967 0.0025" euler="0 0 0.742" size="0.045 0.022 0.0012" rgba="0.95 0.85 0.05 1" contype="0" conaffinity="0"/>
    <geom type="box" pos="-0.193 -0.931 0.0025" euler="0 0 0.752" size="0.041 0.022 0.0012" rgba="0.95 0.85 0.05 1" contype="0" conaffinity="0"/>
    <geom type="box" pos="-0.157 -0.897 0.0025" euler="0 0 0.749" size="0.038 0.022 0.0012" rgba="0.95 0.85 0.05 1" contype="0" conaffinity="0"/>
    <geom type="box" pos="-0.124 -0.867 0.0025" euler="0 0 0.728" size="0.034 0.022 0.0012" rgba="0.95 0.85 0.05 1" contype="0" conaffinity="0"/>
    <geom type="box" pos="-0.093 -0.841 0.0025" euler="0 0 0.683" size="0.030 0.022 0.0012" rgba="0.95 0.85 0.05 1" contype="0" conaffinity="0"/>
    <geom type="box" pos="-0.065 -0.819 0.0025" euler="0 0 0.605" size="0.027 0.022 0.0012" rgba="0.95 0.85 0.05 1" contype="0" conaffinity="0"/>
    <geom type="box" pos="-0.038 -0.803 0.0025" euler="0 0 0.485" size="0.023 0.022 0.0012" rgba="0.95 0.85 0.05 1" contype="0" conaffinity="0"/>
    <geom type="box" pos="-0.013 -0.792 0.0025" euler="0 0 0.318" size="0.021 0.022 0.0012" rgba="0.95 0.85 0.05 1" contype="0" conaffinity="0"/>
    <geom type="box" pos="0.012 -0.786 0.0025" euler="0 0 0.114" size="0.020 0.022 0.0012" rgba="0.95 0.85 0.05 1" contype="0" conaffinity="0"/>
    <geom type="box" pos="0.037 -0.786 0.0025" euler="0 0 -0.098" size="0.020 0.022 0.0012" rgba="0.95 0.85 0.05 1" contype="0" conaffinity="0"/>
    <geom type="box" pos="0.062 -0.791 0.0025" euler="0 0 -0.282" size="0.021 0.022 0.0012" rgba="0.95 0.85 0.05 1" contype="0" conaffinity="0"/>
    <geom type="box" pos="0.089 -0.801 0.0025" euler="0 0 -0.419" size="0.023 0.022 0.0012" rgba="0.95 0.85 0.05 1" contype="0" conaffinity="0"/>
    <geom type="box" pos="0.116 -0.815 0.0025" euler="0 0 -0.511" size="0.026 0.022 0.0012" rgba="0.95 0.85 0.05 1" contype="0" conaffinity="0"/>
    <geom type="box" pos="0.145 -0.832 0.0025" euler="0 0 -0.566" size="0.029 0.022 0.0012" rgba="0.95 0.85 0.05 1" contype="0" conaffinity="0"/>
    <geom type="box" pos="0.177 -0.853 0.0025" euler="0 0 -0.593" size="0.031 0.022 0.0012" rgba="0.95 0.85 0.05 1" contype="0" conaffinity="0"/>
    <geom type="box" pos="0.210 -0.876 0.0025" euler="0 0 -0.598" size="0.034 0.022 0.0012" rgba="0.95 0.85 0.05 1" contype="0" conaffinity="0"/>
    <geom type="box" pos="0.246 -0.900 0.0025" euler="0 0 -0.587" size="0.036 0.022 0.0012" rgba="0.95 0.85 0.05 1" contype="0" conaffinity="0"/>
    <geom type="box" pos="0.285 -0.925 0.0025" euler="0 0 -0.562" size="0.037 0.022 0.0012" rgba="0.95 0.85 0.05 1" contype="0" conaffinity="0"/>
    <geom type="box" pos="0.325 -0.949 0.0025" euler="0 0 -0.527" size="0.039 0.022 0.0012" rgba="0.95 0.85 0.05 1" contype="0" conaffinity="0"/>
    <geom type="box" pos="0.368 -0.973 0.0025" euler="0 0 -0.483" size="0.039 0.022 0.0012" rgba="0.95 0.85 0.05 1" contype="0" conaffinity="0"/>
    <geom type="box" pos="0.412 -0.994 0.0025" euler="0 0 -0.429" size="0.040 0.022 0.0012" rgba="0.95 0.85 0.05 1" contype="0" conaffinity="0"/>
    <geom type="box" pos="0.458 -1.014 0.0025" euler="0 0 -0.368" size="0.040 0.022 0.0012" rgba="0.95 0.85 0.05 1" contype="0" conaffinity="0"/>
    <geom type="box" pos="0.505 -1.030 0.0025" euler="0 0 -0.298" size="0.040 0.022 0.0012" rgba="0.95 0.85 0.05 1" contype="0" conaffinity="0"/>
    <geom type="box" pos="0.552 -1.043 0.0025" euler="0 0 -0.221" size="0.039 0.022 0.0012" rgba="0.95 0.85 0.05 1" contype="0" conaffinity="0"/>
    <geom type="box" pos="0.600 -1.051 0.0025" euler="0 0 -0.136" size="0.038 0.022 0.0012" rgba="0.95 0.85 0.05 1" contype="0" conaffinity="0"/>
    <geom type="box" pos="0.647 -1.055 0.0025" euler="0 0 -0.044" size="0.038 0.022 0.0012" rgba="0.95 0.85 0.05 1" contype="0" conaffinity="0"/>
    <geom type="box" pos="0.693 -1.055 0.0025" euler="0 0 0.054" size="0.037 0.022 0.0012" rgba="0.95 0.85 0.05 1" contype="0" conaffinity="0"/>
    <geom type="box" pos="0.738 -1.050 0.0025" euler="0 0 0.158" size="0.036 0.022 0.0012" rgba="0.95 0.85 0.05 1" contype="0" conaffinity="0"/>
    <geom type="box" pos="0.782 -1.041 0.0025" euler="0 0 0.266" size="0.035 0.022 0.0012" rgba="0.95 0.85 0.05 1" contype="0" conaffinity="0"/>
    <geom type="box" pos="0.823 -1.027 0.0025" euler="0 0 0.377" size="0.035 0.022 0.0012" rgba="0.95 0.85 0.05 1" contype="0" conaffinity="0"/>
    <geom type="box" pos="0.862 -1.009 0.0025" euler="0 0 0.487" size="0.034 0.022 0.0012" rgba="0.95 0.85 0.05 1" contype="0" conaffinity="0"/>
    <geom type="box" pos="0.899 -0.988 0.0025" euler="0 0 0.595" size="0.034 0.022 0.0012" rgba="0.95 0.85 0.05 1" contype="0" conaffinity="0"/>
    <geom type="box" pos="0.932 -0.962 0.0025" euler="0 0 0.698" size="0.034 0.022 0.0012" rgba="0.95 0.85 0.05 1" contype="0" conaffinity="0"/>
    <geom type="box" pos="0.963 -0.934 0.0025" euler="0 0 0.794" size="0.034 0.022 0.0012" rgba="0.95 0.85 0.05 1" contype="0" conaffinity="0"/>
    <geom type="box" pos="0.992 -0.902 0.0025" euler="0 0 0.883" size="0.034 0.022 0.0012" rgba="0.95 0.85 0.05 1" contype="0" conaffinity="0"/>
    <geom type="box" pos="1.017 -0.869 0.0025" euler="0 0 0.961" size="0.034 0.022 0.0012" rgba="0.95 0.85 0.05 1" contype="0" conaffinity="0"/>
    <geom type="box" pos="1.040 -0.833 0.0025" euler="0 0 1.030" size="0.034 0.022 0.0012" rgba="0.95 0.85 0.05 1" contype="0" conaffinity="0"/>
    <geom type="box" pos="1.061 -0.796 0.0025" euler="0 0 1.089" size="0.034 0.022 0.0012" rgba="0.95 0.85 0.05 1" contype="0" conaffinity="0"/>
    <geom type="box" pos="1.079 -0.759 0.0025" euler="0 0 1.138" size="0.034 0.022 0.0012" rgba="0.95 0.85 0.05 1" contype="0" conaffinity="0"/>
    <geom type="box" pos="1.096 -0.720 0.0025" euler="0 0 1.176" size="0.034 0.022 0.0012" rgba="0.95 0.85 0.05 1" contype="0" conaffinity="0"/>
    <geom type="box" pos="1.112 -0.681 0.0025" euler="0 0 1.204" size="0.033 0.022 0.0012" rgba="0.95 0.85 0.05 1" contype="0" conaffinity="0"/>
    <geom type="box" pos="1.126 -0.642 0.0025" euler="0 0 1.223" size="0.033 0.022 0.0012" rgba="0.95 0.85 0.05 1" contype="0" conaffinity="0"/>
    <geom type="box" pos="1.140 -0.604 0.0025" euler="0 0 1.233" size="0.033 0.022 0.0012" rgba="0.95 0.85 0.05 1" contype="0" conaffinity="0"/>
    <geom type="box" pos="1.153 -0.565 0.0025" euler="0 0 1.235" size="0.033 0.022 0.0012" rgba="0.95 0.85 0.05 1" contype="0" conaffinity="0"/>
    <geom type="box" pos="1.167 -0.527 0.0025" euler="0 0 1.231" size="0.032 0.022 0.0012" rgba="0.95 0.85 0.05 1" contype="0" conaffinity="0"/>
    <geom type="box" pos="1.180 -0.489 0.0025" euler="0 0 1.221" size="0.032 0.022 0.0012" rgba="0.95 0.85 0.05 1" contype="0" conaffinity="0"/>
    <geom type="box" pos="1.194 -0.451 0.0025" euler="0 0 1.208" size="0.032 0.022 0.0012" rgba="0.95 0.85 0.05 1" contype="0" conaffinity="0"/>
    <geom type="box" pos="1.209 -0.414 0.0025" euler="0 0 1.193" size="0.032 0.022 0.0012" rgba="0.95 0.85 0.05 1" contype="0" conaffinity="0"/>
    <geom type="box" pos="1.224 -0.377 0.0025" euler="0 0 1.179" size="0.032 0.022 0.0012" rgba="0.95 0.85 0.05 1" contype="0" conaffinity="0"/>
    <geom type="box" pos="1.240 -0.339 0.0025" euler="0 0 1.168" size="0.033 0.022 0.0012" rgba="0.95 0.85 0.05 1" contype="0" conaffinity="0"/>
    <geom type="box" pos="1.256 -0.301 0.0025" euler="0 0 1.161" size="0.033 0.022 0.0012" rgba="0.95 0.85 0.05 1" contype="0" conaffinity="0"/>
    <geom type="box" pos="1.273 -0.263 0.0025" euler="0 0 1.160" size="0.033 0.022 0.0012" rgba="0.95 0.85 0.05 1" contype="0" conaffinity="0"/>
    <geom type="box" pos="1.289 -0.225 0.0025" euler="0 0 1.166" size="0.034 0.022 0.0012" rgba="0.95 0.85 0.05 1" contype="0" conaffinity="0"/>
    <geom type="box" pos="1.306 -0.186 0.0025" euler="0 0 1.179" size="0.034 0.022 0.0012" rgba="0.95 0.85 0.05 1" contype="0" conaffinity="0"/>
    <geom type="box" pos="1.322 -0.146 0.0025" euler="0 0 1.201" size="0.035 0.022 0.0012" rgba="0.95 0.85 0.05 1" contype="0" conaffinity="0"/>
    <geom type="box" pos="1.337 -0.105 0.0025" euler="0 0 1.230" size="0.035 0.022 0.0012" rgba="0.95 0.85 0.05 1" contype="0" conaffinity="0"/>
    <geom type="box" pos="1.351 -0.064 0.0025" euler="0 0 1.268" size="0.035 0.022 0.0012" rgba="0.95 0.85 0.05 1" contype="0" conaffinity="0"/>
    <geom type="box" pos="1.363 -0.021 0.0025" euler="0 0 1.314" size="0.035 0.022 0.0012" rgba="0.95 0.85 0.05 1" contype="0" conaffinity="0"/>
    <body name="obs_0" pos="0 0 -5">
      <freejoint/>
      <geom name="obs_0" type="box" size="0.039 0.039 0.039" material="m0"/>
    </body>
    <body name="obs_1" pos="0 0 -5">
      <freejoint/>
      <geom name="obs_1" type="sphere" size="0.023" material="m1"/>
    </body>
    <body name="obs_2" pos="0 0 -5">
      <freejoint/>
      <geom name="obs_2" type="cylinder" size="0.024 0.036" material="m2"/>
    </body>
    <body name="obs_3" pos="0 0 -5">
      <freejoint/>
      <geom name="obs_3" type="ellipsoid" size="0.034 0.024 0.048" material="m3"/>
    </body>
    <body name="obs_4" pos="0 0 -5">
      <freejoint/>
      <geom name="obs_4" type="capsule" size="0.017 0.024" material="m4"/>
    </body>
    <body name="obs_5" pos="0 0 -5">
      <freejoint/>
      <geom name="obs_5" type="mesh" mesh="pyramid" material="m5"/>
    </body>
    <body name="obs_6" pos="0 0 -5">
      <freejoint/>
      <geom name="obs_6" type="box" size="0.041 0.041 0.041" material="m6"/>
    </body>
    <body name="obs_7" pos="0 0 -5">
      <freejoint/>
      <geom name="obs_7" type="sphere" size="0.041" material="m7"/>
    </body>
    <body name="dyn_p0" mocap="true" pos="-2.4 2.2 0"><geom type="box" pos="0 0 0.92" size="0.16 0.11 0.28" rgba="0.15 0.2 0.45 1" contype="0" conaffinity="0"/><geom type="sphere" pos="0 0 1.32" size="0.11" rgba="0.82 0.66 0.54 1" contype="0" conaffinity="0"/><geom type="box" pos="0 -0.09 0.32" size="0.07 0.06 0.32" rgba="0.1 0.1 0.12 1" contype="0" conaffinity="0"/><geom type="box" pos="0 0.09 0.32" size="0.07 0.06 0.32" rgba="0.1 0.1 0.12 1" contype="0" conaffinity="0"/></body>
    <body name="dyn_p1" mocap="true" pos="2.4 -2.2 0"><geom type="box" pos="0 0 0.92" size="0.16 0.11 0.28" rgba="0.5 0.12 0.12 1" contype="0" conaffinity="0"/><geom type="sphere" pos="0 0 1.32" size="0.11" rgba="0.82 0.66 0.54 1" contype="0" conaffinity="0"/><geom type="box" pos="0 -0.09 0.32" size="0.07 0.06 0.32" rgba="0.1 0.1 0.12 1" contype="0" conaffinity="0"/><geom type="box" pos="0 0.09 0.32" size="0.07 0.06 0.32" rgba="0.1 0.1 0.12 1" contype="0" conaffinity="0"/></body>
    <body name="dyn_p2" mocap="true" pos="-2.2 -2.4 0"><geom type="box" pos="0 0 0.92" size="0.16 0.11 0.28" rgba="0.1 0.3 0.25 1" contype="0" conaffinity="0"/><geom type="sphere" pos="0 0 1.32" size="0.11" rgba="0.82 0.66 0.54 1" contype="0" conaffinity="0"/><geom type="box" pos="0 -0.09 0.32" size="0.07 0.06 0.32" rgba="0.1 0.1 0.12 1" contype="0" conaffinity="0"/><geom type="box" pos="0 0.09 0.32" size="0.07 0.06 0.32" rgba="0.1 0.1 0.12 1" contype="0" conaffinity="0"/></body>
    <body name="dyn_t0" mocap="true" pos="2.6 1.2 0"><geom type="box" pos="0 0 0.74" size="0.6 0.3 0.02" rgba="0.7 0.55 0.35 1" contype="0" conaffinity="0"/><geom type="box" pos="0 0 0.37" size="0.05 0.05 0.37" rgba="0.12 0.12 0.12 1" contype="0" conaffinity="0"/></body>
    <body name="dyn_t1" mocap="true" pos="-2.8 -1.2 0"><geom type="box" pos="0 0 0.74" size="0.6 0.3 0.02" rgba="0.7 0.55 0.35 1" contype="0" conaffinity="0"/><geom type="box" pos="0 0 0.37" size="0.05 0.05 0.37" rgba="0.12 0.12 0.12 1" contype="0" conaffinity="0"/></body>
    <body name="base" pos="1.368 0.000 0.028" euler="0 0 1.368">
      <freejoint name="root"/>
      <geom name="shell" type="ellipsoid" size="0.10 0.10 0.045" pos="0 0 0.037" rgba="1.0 0.93 0.55 1" mass="0.9"/>
      <geom name="nose" type="box" size="0.022 0.012 0.008" pos="0.092 0 0.03" rgba="0.95 0.45 0.1 1" mass="0.001"/>
      <site name="imu" pos="0 0 0.04" size="0.004"/>
      <body name="cam_mast" pos="0.06 0 0.12">
        <joint name="cam_pan" class="camlink" type="hinge" axis="0 0 1" range="-1.2 1.2"/>
        <geom class="camlink" type="cylinder" size="0.006 0.015" mass="0.01"/>
        <body name="cam_tilt" pos="0 0 0.015">
          <joint name="cam_tilt" class="camlink" type="hinge" axis="0 1 0" range="-0.5 1.0"/>
          <geom class="camlink" type="box" size="0.012 0.02 0.01" mass="0.01"/>
          <camera name="eye" pos="0.02 0 0" fovy="90" xyaxes="0 -1 0  0.7071 0 0.7071"/>
        </body>
      </body>
      <body name="left_wheel" pos="-0.01 0.085 0"><joint name="left_wheel" class="wheel"/><geom class="wheel"/></body>
      <body name="right_wheel" pos="-0.01 -0.085 0"><joint name="right_wheel" class="wheel"/><geom class="wheel"/></body>
      <geom name="front_caster" class="caster" pos="0.075 0 -0.018"/>
      <geom name="rear_caster"  class="caster" pos="-0.075 0 -0.018"/>
    </body>
  </worldbody>
  <contact>
    <exclude body1="base" body2="left_wheel"/><exclude body1="base" body2="right_wheel"/>
  </contact>
  <actuator>
    <velocity name="left_motor"  joint="left_wheel"  kv="5.0" ctrlrange="-22 22"/>
    <velocity name="right_motor" joint="right_wheel" kv="5.0" ctrlrange="-22 22"/>
    <position name="pan_servo"  joint="cam_pan"  kp="6" ctrlrange="-1.2 1.2"/>
    <position name="tilt_servo" joint="cam_tilt" kp="6" ctrlrange="-0.5 1.0"/>
  </actuator>
  <sensor>
    <gyro name="gyro" site="imu"/>
    <framepos name="base_pos" objtype="site" objname="imu"/>
    <framequat name="base_quat" objtype="site" objname="imu"/>
  </sensor>
</mujoco>
